ADDSUB/Full_A.vhdl
library ieee;
use ieee.std_logic_1164.all;

entity Full_A is
    port(
        A,B,Cin: in std_logic;
        Cout,S : out std_logic
    );
end entity Full_A;

architecture arch of Full_A is
signal D,E,F: std_logic;
begin
    D<= A xor B;
    E<= Cin and D;
    F<= A and B;
    S<= Cin xor D;
    Cout <= E or F;
end arch;

ADDSUB/addsub.vhdl
library ieee;
use ieee.std_logic_1164.all;

entity addsub is
    port(
        A,B: in std_logic_vector(7 downto 0);
        T: in std_logic;
        OV_FLAG, C_FLAG : out std_logic;
        R: out std_logic_vector(7 downto 0)
    );
end entity addsub;

architecture arch of addsub is
    component Full_A
        port(
            A,B,Cin: in std_logic;
            Cout,S : out std_logic
        );
    end component;
signal B_T: std_logic_vector(7 downto 0);
signal C_O: std_logic_vector(7 downto 0);
begin
    B_T(0) <= B(0) xor T;
    B_T(1) <= B(1) xor T;
    B_T(2) <= B(2) xor T;
    B_T(3) <= B(3) xor T;
    B_T(4) <= B(4) xor T;
    B_T(5) <= B(5) xor T;
    B_T(6) <= B(6) xor T;
    B_T(7) <= B(7) xor T;
    FS0: FULL_A port map (A=>A(0),B=>B_T(0),Cin=> T,     Cout=>C_O(0),S=>R(0));
    FS1: FULL_A port map (A=>A(1),B=>B_T(1),Cin=> C_O(0),Cout=>C_O(1),S=>R(1));
    FS2: FULL_A port map (A=>A(2),B=>B_T(2),Cin=> C_O(1),Cout=>C_O(2),S=>R(2));
    FS3: FULL_A port map (A=>A(3),B=>B_T(3),Cin=> C_O(2),Cout=>C_O(3),S=>R(3));
    FS4: FULL_A port map (A=>A(4),B=>B_T(4),Cin=> C_O(3),Cout=>C_O(4),S=>R(4));
    FS5: FULL_A port map (A=>A(5),B=>B_T(5),Cin=> C_O(4),Cout=>C_O(5),S=>R(5));
    FS6: FULL_A port map (A=>A(6),B=>B_T(6),Cin=> C_O(5),Cout=>C_O(6),S=>R(6));
    FS7: FULL_A port map (A=>A(7),B=>B_T(7),Cin=> C_O(6),Cout=>C_O(7),S=>R(7));
    C_FLAG  <=C_O(7);
    OV_FLAG <=C_O(7) xor C_O(6);
end arch;

ADDSUB/addsub_tb.vhdl
library ieee;
use ieee.std_logic_1164.all;

entity addsub_tb is 
end addsub_tb;

architecture arch of addsub_tb is
    component addsub is 
        port(
            A,B: in std_logic_vector(7 downto 0);
            T: in std_logic;
            OV_FLAG, C_FLAG : out std_logic;
            R: out std_logic_vector(7 downto 0)
        );
    end component;
    signal A,B: std_logic_vector(7 downto 0);
    signal T: std_logic;
    signal OV_FLAG, C_FLAG : std_logic;
    signal R: std_logic_vector(7 downto 0);
begin
    FS0 : addsub port map (A,B,T,OV_FLAG,C_FLAG,R);
    process
    begin
        --SUMA POSITIVO/POSITIVO
        T<='0';
        A<="00001111";
        B<="00001111";
        wait for 5 ns;
        A<="00000001";
        B<="00001111";
        wait for 5 ns;
        --SUMA POSITIVO/NEGATIVO
        A<="00011111";
        B<="10001111";
        wait for 5 ns;
        A<="00000001";
        B<="11111111";
        wait for 5 ns;
        --SUMA NEGATIVO/POSITIVO
        A<="10001111";
        B<="00011111";
        wait for 5 ns;
        A<="11111111";
        B<="00000001";
        wait for 5 ns;
        --SUMA OVERFLOW
        A<="01111111";
        B<="00000001";
        wait for 5 ns;
        A<="11111111";
        B<="10000000";
        wait for 5 ns;
        --RESTA OVERFLOW
        T<='1';
        A<="01111111";
        B<="11111111";
        wait for 5 ns;
        A<="10000000";
        B<="00000001";
        wait for 5 ns;
        --SUMA COUT
        T<='0';
        A<="11111111";
        B<="10000001";
        wait for 5 ns;
        A<="10001000";
        B<="10001000";
        wait for 5 ns;
        --RESTA COUT
        T<='1';
        A<="11111111";
        B<="00000001";
        wait for 5 ns;
        A<="10001000";
        B<="00000001";
        wait for 5 ns;
        wait; 
        
    end process; 
end arch;

ADDSUB/addsub_tb.vcd
$date
  Mon Mar 30 17:37:59 2020
$end
$version
  GHDL v0
$end
$timescale
  1 fs
$end
$scope module standard $end
$upscope $end
$scope module std_logic_1164 $end
$upscope $end
$scope module addsub_tb $end
$var reg 8 ! a[7:0] $end
$var reg 8 " b[7:0] $end
$var reg 1 # t $end
$var reg 1 $ ov_flag $end
$var reg 1 % c_flag $end
$var reg 8 & r[7:0] $end
$scope module fs0 $end
$var reg 8 ' a[7:0] $end
$var reg 8 ( b[7:0] $end
$var reg 1 ) t $end
$var reg 1 * ov_flag $end
$var reg 1 + c_flag $end
$var reg 8 , r[7:0] $end
$var reg 8 - b_t[7:0] $end
$var reg 8 . c_o[7:0] $end
$scope module fs0 $end
$var reg 1 / a $end
$var reg 1 0 b $end
$var reg 1 1 cin $end
$var reg 1 2 cout $end
$var reg 1 3 s $end
$var reg 1 4 d $end
$var reg 1 5 e $end
$var reg 1 6 f $end
$upscope $end
$scope module fs1 $end
$var reg 1 7 a $end
$var reg 1 8 b $end
$var reg 1 9 cin $end
$var reg 1 : cout $end
$var reg 1 ; s $end
$var reg 1 < d $end
$var reg 1 = e $end
$var reg 1 > f $end
$upscope $end
$scope module fs2 $end
$var reg 1 ? a $end
$var reg 1 @ b $end
$var reg 1 A cin $end
$var reg 1 B cout $end
$var reg 1 C s $end
$var reg 1 D d $end
$var reg 1 E e $end
$var reg 1 F f $end
$upscope $end
$scope module fs3 $end
$var reg 1 G a $end
$var reg 1 H b $end
$var reg 1 I cin $end
$var reg 1 J cout $end
$var reg 1 K s $end
$var reg 1 L d $end
$var reg 1 M e $end
$var reg 1 N f $end
$upscope $end
$scope module fs4 $end
$var reg 1 O a $end
$var reg 1 P b $end
$var reg 1 Q cin $end
$var reg 1 R cout $end
$var reg 1 S s $end
$var reg 1 T d $end
$var reg 1 U e $end
$var reg 1 V f $end
$upscope $end
$scope module fs5 $end
$var reg 1 W a $end
$var reg 1 X b $end
$var reg 1 Y cin $end
$var reg 1 Z cout $end
$var reg 1 [ s $end
$var reg 1 \ d $end
$var reg 1 ] e $end
$var reg 1 ^ f $end
$upscope $end
$scope module fs6 $end
$var reg 1 _ a $end
$var reg 1 ` b $end
$var reg 1 a cin $end
$var reg 1 b cout $end
$var reg 1 c s $end
$var reg 1 d d $end
$var reg 1 e e $end
$var reg 1 f f $end
$upscope $end
$scope module fs7 $end
$var reg 1 g a $end
$var reg 1 h b $end
$var reg 1 i cin $end
$var reg 1 j cout $end
$var reg 1 k s $end
$var reg 1 l d $end
$var reg 1 m e $end
$var reg 1 n f $end
$upscope $end
$upscope $end
$upscope $end
$enddefinitions $end
#0
b00001111 !
b00001111 "
0#
0$
0%
b00011110 &
b00001111 '
b00001111 (
0)
0*
0+
b00011110 ,
b00001111 -
b00001111 .
1/
10
01
12
03
04
05
16
17
18
19
1:
1;
0<
0=
1>
1?
1@
1A
1B
1C
0D
0E
1F
1G
1H
1I
1J
1K
0L
0M
1N
0O
0P
1Q
0R
1S
0T
0U
0V
0W
0X
0Y
0Z
0[
0\
0]
0^
0_
0`
0a
0b
0c
0d
0e
0f
0g
0h
0i
0j
0k
0l
0m
0n
#5000000
b00000001 !
b00010000 &
b00000001 '
b00010000 ,
b00001111 .
07
1:
0;
1<
1=
0>
0?
1A
1B
0C
1D
1E
0F
0G
1I
1J
0K
1L
1M
0N
1Q
1S
#10000000
b00011111 !
b10001111 "
b10101110 &
b00011111 '
b10001111 (
b10101110 ,
b10001111 -
b00011111 .
17
1;
0<
0=
1>
1?
1C
0D
0E
1F
1G
1K
0L
0M
1N
1O
1R
0S
1T
1U
1Y
1[
1h
1k
1l
#15000000
b00000001 !
b11111111 "
0$
1%
b00000000 &
b00000001 '
b11111111 (
0*
1+
b00000000 ,
b11111111 -
b11111111 .
07
1:
0;
1<
1=
0>
0?
1A
1B
0C
1D
1E
0F
0G
1I
1J
0K
1L
1M
0N
0O
1P
1Q
1R
0S
1T
1U
1X
1Y
1Z
0[
1\
1]
1`
1a
1b
0c
1d
1e
1i
1j
0k
1m
#20000000
b10001111 !
b00011111 "
0$
0%
b10101110 &
b10001111 '
b00011111 (
0*
0+
b10101110 ,
b00011111 -
b00011111 .
17
1;
0<
0=
1>
1?
1C
0D
0E
1F
1G
1K
0L
0M
1N
0X
0Z
1[
0\
0]
0`
0a
0b
0c
0d
0e
1g
0h
0i
0j
1k
1l
0m
0n
#25000000
b11111111 !
b00000001 "
0$
1%
b00000000 &
b11111111 '
b00000001 (
0*
1+
b00000000 ,
b00000001 -
b11111111 .
08
1:
0;
1<
1=
0>
0@
1A
1B
0C
1D
1E
0F
0H
1I
1J
0K
1L
1M
0N
1O
0P
1Q
1R
0S
1T
1U
0V
1W
1Y
1Z
0[
1\
1]
1_
1a
1b
0c
1d
1e
1i
1j
0k
1m
#30000000
b01111111 !
1$
0%
b10000000 &
b01111111 '
1*
0+
b10000000 ,
b01111111 .
0g
0j
1k
0l
0m
#35000000
b11111111 !
b10000000 "
1$
1%
b01111111 &
b11111111 '
b10000000 (
1*
1+
b01111111 ,
b10000000 -
b10000000 .
00
02
13
14
06
09
0:
1;
0=
0A
0B
1C
0E
0I
0J
1K
0M
0Q
0R
1S
0U
0Y
0Z
1[
0]
0a
0b
1c
0e
1g
1h
0i
1j
0k
0l
0m
1n
#40000000
b01111111 !
b11111111 "
1#
1$
0%
b10000000 &
b01111111 '
b11111111 (
1)
1*
0+
b10000000 ,
b00000000 -
b01111111 .
11
12
03
15
19
1:
0;
1=
1A
1B
0C
1E
1I
1J
0K
1M
1Q
1R
0S
1U
1Y
1Z
0[
1]
1a
1b
0c
1e
0g
0h
1i
0j
1k
0l
0n
#45000000
b10000000 !
b00000001 "
1$
1%
b01111111 &
b10000000 '
b00000001 (
1*
1+
b01111111 ,
b11111110 -
b10000000 .
0/
02
13
04
05
07
18
09
0:
1;
1<
0=
0?
1@
0A
0B
1C
1D
0E
0G
1H
0I
0J
1K
1L
0M
0O
1P
0Q
0R
1S
1T
0U
0W
1X
0Y
0Z
1[
1\
0]
0_
1`
0a
0b
1c
1d
0e
1g
1h
0i
1j
0k
0l
0m
1n
#50000000
b11111111 !
b10000001 "
0#
0$
b10000000 &
b11111111 '
b10000001 (
0)
0*
b10000000 ,
b10000001 -
b11111111 .
1/
10
01
12
03
04
16
17
08
19
1:
0;
1<
1=
0>
1?
0@
1A
1B
0C
1D
1E
0F
1G
0H
1I
1J
0K
1L
1M
0N
1O
0P
1Q
1R
0S
1T
1U
0V
1W
0X
1Y
1Z
0[
1\
1]
0^
1_
0`
1a
1b
0c
1d
1e
0f
1i
1k
#55000000
b10001000 !
b10001000 "
1$
b00010000 &
b10001000 '
b10001000 (
1*
b00010000 ,
b10001000 -
b10001000 .
0/
00
02
03
04
06
07
09
0:
0;
0<
0=
0?
0A
0B
0C
0D
0E
1H
0I
0K
0L
0M
1N
0O
0R
1S
0T
0U
0W
0Y
0Z
0[
0\
0]
0_
0a
0b
0c
0d
0e
0i
0k
#60000000
b11111111 !
b00000001 "
1#
0$
b11111110 &
b11111111 '
b00000001 (
1)
0*
b11111110 ,
b11111110 -
b11111111 .
1/
11
12
03
14
15
17
18
19
1:
1;
0<
1>
1?
1@
1A
1B
1C
0D
1F
1I
1K
1O
1P
1R
1S
0T
0U
1V
1W
1X
1Y
1Z
1[
0\
1^
1_
1`
1a
1b
1c
0d
1f
1i
1k
#65000000
b10001000 !
0$
b10000111 &
b10001000 '
0*
b10000111 ,
b11111000 .
0/
02
13
04
05
07
09
0:
1;
1<
0=
0>
0?
0A
0B
1C
1D
0E
0F
0I
0K
0O
1R
0S
1T
1U
0V
0W
1Y
1Z
0[
1\
1]
0^
0_
1a
1b
0c
1d
1e
0f
1i
1k
