Practice4/decoder7.vhdl
entity decoder7 is
    port(
        S:in bit_vector(3 downto 0);
        Z:out bit_vector(6 downto 0)
    );
end decoder7;

architecture arch of decoder7 is
    signal Ands: bit_vector(9 downto 1);
    signal A,B,C,D:bit;
begin
    A<=S(0);
    B<=S(1);
    C<=S(2);
    D<=S(3);

    Ands(1)<= B and D;
    Ands(2)<= not B and not D;
    Ands(3)<= C and D;
    Ands(4)<= not C and not D;
    Ands(5)<= C and not D;
    Ands(6)<= not B and C;
    Ands(7)<= B and not C and D;
    Ands(8)<= B and not C;
    Ands(9)<= B and not D;

    Z(0)<= A or C or Ands(1) or Ands(2);
    Z(1)<= not B or Ands(4) or Ands(3);
    Z(2)<= B or D or not C;
    Z(3)<= A or Ands(2) or Ands(7) or Ands(5) or Ands(6);
    Z(4)<= Ands(2) or Ands(5);
    Z(5)<= A or Ands(4) or Ands(8) or Ands(9);
    Z(6)<= A or Ands(5) or Ands(8) or Ands(6);

end arch;

Practice4/Multiplexor4_1.vhdl
entity Multiplexor4_1 is
    port(
        A: in bit_vector(3 downto 0);
        S: in bit_vector(1 downto 0);
        Z: out bit
    );
end entity;

architecture arch of Multiplexor4_1 is
signal notS: bit_vector(1 downto 0);
signal temp: bit_vector(3 downto 0);
begin
    notS(0)<= not S(0);
    notS(1)<= not S(1);
    temp(0)<=(A(0) and notS(0) and notS(1));
    temp(1)<=(A(1) and notS(1) and S(0));
    temp(2)<=(A(2) and notS(0) and S(1));
    temp(3)<=(A(3) and S(0) and S(1));
    Z<= (temp(0) or temp(1) or temp(2) or temp(3)); 
end arch;

Practice4/FF_JK.vhdl
entity FF_JK is
    port(
        CLK,J,K,PRESET,CLEAR,EN: in bit;
        Q,Qn: out bit
        );
end entity;
 
architecture arch of FF_JK is
    signal intQ: bit;
begin
    Q<=intQ;
    Qn<=not intQ;
    process(CLK,PRESET,CLEAR)
        begin

        if EN='0' then
            null;
        elsif CLEAR='0' then
            intQ<='0';
        elsif PRESET='0' then
            intQ<='1';
        elsif CLK'event and CLK='1' then
            if J = '0' and K = '0' then
                intQ <= intQ;
            elsif J = '0' and K = '1' then
                intQ <= '0';
            elsif J = '1' and K = '0' then
                intQ <= '1';
            else
                intQ <= not intQ;
            end if;
        end if;
    end process;
end arch;

Practice4/Counter2B.vhdl
entity Counter2B is
    port(
        CLK: in bit;
        CLEAR: in bit;
        PRESET: in bit;
        EN: in bit;
        Z: out bit_vector(1 downto 0)
        );
end Counter2B;
 
architecture arch of Counter2B is
    component FF_JK is
        port(
            CLK,J,K,PRESET,CLEAR,EN: in bit;
            Q,Qn: out bit
            );
    end component;
    signal intQ: bit_vector(1 downto 0);
    signal intQN: bit_vector(1 downto 0);
    signal intJK: bit_vector(1 downto 0);
begin
    intJK(0)<='1';
    intJK(1)<=intQ(0);
    F0: FF_JK port map(CLK=>CLK,J=>intJK(0),K=>intJK(0),PRESET=>PRESET,CLEAR=>CLEAR,Q=>intQ(0),Qn=>intQN(0),EN=>EN);
    F1: FF_JK port map(CLK=>CLK,J=>intJK(1),K=>intJK(1),PRESET=>PRESET,CLEAR=>CLEAR,Q=>intQ(1),Qn=>intQN(1),EN=>EN);
    Z(0)<=intQ(0);
    Z(1)<=intQ(1);
    
end arch;

Practice4/controller.vhdl
entity controller is
    port(
        CLK: in bit;
        CLEAR: in bit;
        A: in bit_vector(15 downto 0);
        D: in bit_vector(3 downto 0);
        Z1: out bit_vector(7 downto 0);
        Z2: out bit_vector(7 downto 0);
        Z3: out bit_vector(7 downto 0);
        Z4: out bit_vector(7 downto 0)
    );
end controller;

architecture arch of controller is
    component Counter2B is
        port(
            CLK: in bit;
            CLEAR: in bit;
            PRESET: in bit;
            EN: in bit;
            Z: out bit_vector(1 downto 0)
            );
    end component;
    component Multiplexor4_1 is
        port(
            A: in bit_vector(3 downto 0);
            S: in bit_vector(1 downto 0);
            Z: out bit
        );
    end component;
    component decoder7 is
        port(
            S:in bit_vector(3 downto 0);
            Z:out bit_vector(6 downto 0)
        );
    end component;
    signal ENs: bit_vector(3 downto 0);
    signal Zint: bit_vector(1 downto 0);
    --4 BITS AND DECIMAL POINT
    signal Act: bit_vector(4 downto 0);
    --A-G
    signal ActD: bit_vector(6 downto 0);
begin
    FS0:Counter2B port map(CLK,CLEAR,'1','1',Zint);
    
    --Enables Displays
    ENs(0)<=not Zint(0) and not Zint(1);
    ENs(1)<=    Zint(0) and not Zint(1);
    ENs(2)<=not Zint(0) and     Zint(1);
    ENs(3)<=    Zint(0) and     Zint(1);
    
    --Multiplexing of bits
    MS0:Multiplexor4_1 port map( A(0)=>A(0) ,A(1)=>A(4), A(2)=>A(8) , A(3)=>A(12),S=>Zint,Z=>Act(3));
    MS1:Multiplexor4_1 port map( A(0)=>A(1) ,A(1)=>A(5), A(2)=>A(9) , A(3)=>A(13),S=>Zint,Z=>Act(2));
    MS2:Multiplexor4_1 port map( A(0)=>A(2) ,A(1)=>A(6), A(2)=>A(10), A(3)=>A(14),S=>Zint,Z=>Act(1));
    MS3:Multiplexor4_1 port map( A(0)=>A(3) ,A(1)=>A(7), A(2)=>A(11), A(3)=>A(15),S=>Zint,Z=>Act(0));
    MS4:Multiplexor4_1 port map( A(0)=>D(0) ,A(1)=>D(1), A(2)=>D(2),  A(3)=>D(3) ,S=>Zint,Z=>Act(4));
    
    --DECODER
    DS0:decoder7 port map(S(0)=>Act(0), S(1)=>Act(1), S(2)=>Act(2), S(3)=>Act(3),Z=>ActD);
    
    Z1(7)<=ENs(0) and Act(4);
    Z1(6)<=ENs(0) and ActD(6);
    Z1(5)<=ENs(0) and ActD(5);
    Z1(4)<=ENs(0) and ActD(4);
    Z1(3)<=ENs(0) and ActD(3);
    Z1(2)<=ENs(0) and ActD(2);
    Z1(1)<=ENs(0) and ActD(1);
    Z1(0)<=ENs(0) and ActD(0);
    
    Z2(7)<=ENs(1) and Act(4);
    Z2(6)<=ENs(1) and ActD(6);
    Z2(5)<=ENs(1) and ActD(5);
    Z2(4)<=ENs(1) and ActD(4);
    Z2(3)<=ENs(1) and ActD(3);
    Z2(2)<=ENs(1) and ActD(2);
    Z2(1)<=ENs(1) and ActD(1);
    Z2(0)<=ENs(1) and ActD(0);

    Z3(7)<=ENs(2) and Act(4);
    Z3(6)<=ENs(2) and ActD(6);
    Z3(5)<=ENs(2) and ActD(5);
    Z3(4)<=ENs(2) and ActD(4);
    Z3(3)<=ENs(2) and ActD(3);
    Z3(2)<=ENs(2) and ActD(2);
    Z3(1)<=ENs(2) and ActD(1);
    Z3(0)<=ENs(2) and ActD(0);

    Z4(7)<=ENs(3) and Act(4);
    Z4(6)<=ENs(3) and ActD(6);
    Z4(5)<=ENs(3) and ActD(5);
    Z4(4)<=ENs(3) and ActD(4);
    Z4(3)<=ENs(3) and ActD(3);
    Z4(2)<=ENs(3) and ActD(2);
    Z4(1)<=ENs(3) and ActD(1);
    Z4(0)<=ENs(3) and ActD(0);
     

    end arch;

Practice4/controller_tb.vhdl
entity controller_tb is
end controller_tb;

architecture arch of controller_tb is
    component controller is
        port(
            CLK: in bit;
            CLEAR: in bit;
            A: in bit_vector(15 downto 0);
            D: in bit_vector(3 downto 0);
            --DP,G,F,E,D,C,B,A
            Z1: out bit_vector(7 downto 0);
            Z2: out bit_vector(7 downto 0);
            Z3: out bit_vector(7 downto 0);
            Z4: out bit_vector(7 downto 0)
        );
    end component;
    signal CLK: bit;
    signal CLEAR: bit;
    signal A: bit_vector(15 downto 0);
    signal D: bit_vector(3 downto 0);
    signal Z1: bit_vector(7 downto 0);
    signal Z2: bit_vector(7 downto 0);
    signal Z3: bit_vector(7 downto 0);
    signal Z4: bit_vector(7 downto 0);
    
begin
    FS0:controller port map(CLK,CLEAR,A,D,Z1,Z2,Z3,Z4);
    
    CLK_process : process
    begin
        CLK<='0';
        wait for 5 ns;
        CLK<='1';
        wait for 5 ns;
    end process;

    Set_process : process
    begin
        CLEAR<='0';
        wait for 10 ns;
        CLEAR<='1';
        A<="1000000000000001";
        D<="0100";
        wait for 40 ns;
        A<="0010000110001001";
        D<="0010";
        wait for 40 ns;
        wait;
    end process;
    
end arch;

Practice4/controller_tb.vcd
$date
  Tue Mar 31 12:14:07 2020
$end
$version
  GHDL v0
$end
$timescale
  1 fs
$end
$scope module standard $end
$upscope $end
$scope module controller_tb $end
$var reg 1 ! clk $end
$var reg 1 " clear $end
$var reg 16 # a[15:0] $end
$var reg 4 $ d[3:0] $end
$var reg 8 % z1[7:0] $end
$var reg 8 & z2[7:0] $end
$var reg 8 ' z3[7:0] $end
$var reg 8 ( z4[7:0] $end
$scope module fs0 $end
$var reg 1 ) clk $end
$var reg 1 * clear $end
$var reg 16 + a[15:0] $end
$var reg 4 , d[3:0] $end
$var reg 8 - z1[7:0] $end
$var reg 8 . z2[7:0] $end
$var reg 8 / z3[7:0] $end
$var reg 8 0 z4[7:0] $end
$var reg 4 1 ens[3:0] $end
$var reg 2 2 zint[1:0] $end
$var reg 5 3 act[4:0] $end
$var reg 7 4 actd[6:0] $end
$scope module fs0 $end
$var reg 1 5 clk $end
$var reg 1 6 clear $end
$var reg 1 7 preset $end
$var reg 1 8 en $end
$var reg 2 9 z[1:0] $end
$var reg 2 : intq[1:0] $end
$var reg 2 ; intqn[1:0] $end
$var reg 2 < intjk[1:0] $end
$scope module f0 $end
$var reg 1 = clk $end
$var reg 1 > j $end
$var reg 1 ? k $end
$var reg 1 @ preset $end
$var reg 1 A clear $end
$var reg 1 B en $end
$var reg 1 C q $end
$var reg 1 D qn $end
$var reg 1 E intq $end
$upscope $end
$scope module f1 $end
$var reg 1 F clk $end
$var reg 1 G j $end
$var reg 1 H k $end
$var reg 1 I preset $end
$var reg 1 J clear $end
$var reg 1 K en $end
$var reg 1 L q $end
$var reg 1 M qn $end
$var reg 1 N intq $end
$upscope $end
$upscope $end
$scope module ms0 $end
$var reg 4 O a[3:0] $end
$var reg 2 P s[1:0] $end
$var reg 1 Q z $end
$var reg 2 R nots[1:0] $end
$var reg 4 S temp[3:0] $end
$upscope $end
$scope module ms1 $end
$var reg 4 T a[3:0] $end
$var reg 2 U s[1:0] $end
$var reg 1 V z $end
$var reg 2 W nots[1:0] $end
$var reg 4 X temp[3:0] $end
$upscope $end
$scope module ms2 $end
$var reg 4 Y a[3:0] $end
$var reg 2 Z s[1:0] $end
$var reg 1 [ z $end
$var reg 2 \ nots[1:0] $end
$var reg 4 ] temp[3:0] $end
$upscope $end
$scope module ms3 $end
$var reg 4 ^ a[3:0] $end
$var reg 2 _ s[1:0] $end
$var reg 1 ` z $end
$var reg 2 a nots[1:0] $end
$var reg 4 b temp[3:0] $end
$upscope $end
$scope module ms4 $end
$var reg 4 c a[3:0] $end
$var reg 2 d s[1:0] $end
$var reg 1 e z $end
$var reg 2 f nots[1:0] $end
$var reg 4 g temp[3:0] $end
$upscope $end
$scope module ds0 $end
$var reg 4 h s[3:0] $end
$var reg 7 i z[6:0] $end
$var reg 9 j ands[9:1] $end
$var reg 1 k a $end
$var reg 1 l b $end
$var reg 1 m c $end
$var reg 1 n d $end
$upscope $end
$upscope $end
$upscope $end
$enddefinitions $end
#0
0!
0"
b0000000000000000 #
b0000 $
b00111111 %
b00000000 &
b00000000 '
b00000000 (
0)
0*
b0000000000000000 +
b0000 ,
b00111111 -
b00000000 .
b00000000 /
b00000000 0
b0001 1
b00 2
b00000 3
b0111111 4
05
06
17
18
b00 9
b00 :
b11 ;
b01 <
0=
1>
1?
1@
0A
1B
0C
1D
0E
0F
0G
0H
1I
0J
1K
0L
1M
0N
b0000 O
b00 P
0Q
b11 R
b0000 S
b0000 T
b00 U
0V
b11 W
b0000 X
b0000 Y
b00 Z
0[
b11 \
b0000 ]
b0000 ^
b00 _
0`
b11 a
b0000 b
b0000 c
b00 d
0e
b11 f
b0000 g
b0000 h
b0111111 i
b000001010 j
0k
0l
0m
0n
#5000000
1!
1)
15
1=
1F
#10000000
0!
1"
b1000000000000001 #
b0100 $
b00000110 %
0)
1*
b1000000000000001 +
b0100 ,
b00000110 -
b01000 3
b0000110 4
05
16
0=
1A
0F
1J
b0001 O
1Q
b0001 S
b1000 ^
b0100 c
b1000 h
b0000110 i
b000000000 j
1n
#15000000
1!
b00000000 %
b00111111 &
1)
b00000000 -
b00111111 .
b0010 1
b01 2
b00000 3
b0111111 4
15
b01 9
b01 :
b10 ;
b11 <
1=
1C
0D
1E
1F
1G
1H
b01 P
0Q
b10 R
b0000 S
b01 U
b10 W
b01 Z
b10 \
b01 _
b10 a
b01 d
b10 f
b0000 h
b0111111 i
b000001010 j
0n
#20000000
0!
0)
05
0=
0F
#25000000
1!
b00000000 &
b10111111 '
1)
b00000000 .
b10111111 /
b0100 1
b10 2
b10000 3
15
b10 9
b10 :
b01 ;
b01 <
1=
0C
1D
0E
1F
0G
0H
1L
0M
1N
b10 P
b01 R
b10 U
b01 W
b10 Z
b01 \
b10 _
b01 a
b10 d
1e
b01 f
b0100 g
#30000000
0!
0)
05
0=
0F
#35000000
1!
b00000000 '
b01111111 (
1)
b00000000 /
b01111111 0
b1000 1
b11 2
b00001 3
b1111111 4
15
b11 9
b11 :
b00 ;
b11 <
1=
1C
0D
1E
1F
1G
1H
b11 P
b00 R
b11 U
b00 W
b11 Z
b00 \
b11 _
1`
b00 a
b1000 b
b11 d
0e
b00 f
b0000 g
b0001 h
b1111111 i
1k
#40000000
0!
0)
05
0=
0F
#45000000
1!
b00000110 %
b00000000 (
1)
b00000110 -
b00000000 0
b0001 1
b00 2
b01000 3
b0000110 4
15
b00 9
b00 :
b11 ;
b01 <
1=
0C
1D
0E
1F
0G
0H
0L
1M
0N
b00 P
1Q
b11 R
b0001 S
b00 U
b11 W
b00 Z
b11 \
b00 _
0`
b11 a
b0000 b
b00 d
b11 f
b1000 h
b0000110 i
b000000000 j
0k
1n
#50000000
0!
b0010000110001001 #
b0010 $
b01101111 %
0)
b0010000110001001 +
b0010 ,
b01101111 -
b01001 3
b1101111 4
05
0=
0F
b0101 O
b1000 T
b0011 ^
1`
b0001 b
b0010 c
b1001 h
b1101111 i
1k
#55000000
1!
b00000000 %
b11111111 &
1)
b00000000 -
b11111111 .
b0010 1
b01 2
b10001 3
b1111111 4
15
b01 9
b01 :
b10 ;
b11 <
1=
1C
0D
1E
1F
1G
1H
b01 P
0Q
b10 R
b0000 S
b01 U
b10 W
b01 Z
b10 \
b01 _
b10 a
b0010 b
b01 d
1e
b10 f
b0010 g
b0001 h
b1111111 i
b000001010 j
0n
#60000000
0!
0)
05
0=
0F
#65000000
1!
b00000000 &
b00000110 '
1)
b00000000 .
b00000110 /
b0100 1
b10 2
b01000 3
b0000110 4
15
b10 9
b10 :
b01 ;
b01 <
1=
0C
1D
0E
1F
0G
0H
1L
0M
1N
b10 P
1Q
b01 R
b0100 S
b10 U
b01 W
b10 Z
b01 \
b10 _
0`
b01 a
b0000 b
b10 d
0e
b01 f
b0000 g
b1000 h
b0000110 i
b000000000 j
0k
1n
#70000000
0!
0)
05
0=
0F
#75000000
1!
b00000000 '
b01011011 (
1)
b00000000 /
b01011011 0
b1000 1
b11 2
b00100 3
b1011011 4
15
b11 9
b11 :
b00 ;
b11 <
1=
1C
0D
1E
1F
1G
1H
b11 P
0Q
b00 R
b0000 S
b11 U
1V
b00 W
b1000 X
b11 Z
b00 \
b11 _
b00 a
b11 d
b00 f
b0100 h
b1011011 i
b000110010 j
1m
0n
#80000000
0!
0)
05
0=
0F
#85000000
1!
b01101111 %
b00000000 (
1)
b01101111 -
b00000000 0
b0001 1
b00 2
b01001 3
b1101111 4
15
b00 9
b00 :
b11 ;
b01 <
1=
0C
1D
0E
1F
0G
0H
0L
1M
0N
b00 P
1Q
b11 R
b0001 S
b00 U
0V
b11 W
b0000 X
b00 Z
b11 \
b00 _
1`
b11 a
b0001 b
b00 d
b11 f
b1001 h
b1101111 i
b000000000 j
1k
0m
1n
#90000000
0!
0)
05
0=
0F
#95000000
1!
b00000000 %
b11111111 &
1)
b00000000 -
b11111111 .
b0010 1
b01 2
b10001 3
b1111111 4
15
b01 9
b01 :
b10 ;
b11 <
1=
1C
0D
1E
1F
1G
1H
b01 P
0Q
b10 R
b0000 S
b01 U
b10 W
b01 Z
b10 \
b01 _
b10 a
b0010 b
b01 d
1e
b10 f
b0010 g
b0001 h
b1111111 i
b000001010 j
0n
