Practice4/decoder7.vhdl
entity decoder7 is
    port(
        S:in bit_vector(3 downto 0);
        Z:out bit_vector(6 downto 0)
    );
end decoder7;

architecture arch of decoder7 is
    signal Ands: bit_vector(9 downto 1);
    signal A,B,C,D:bit;
begin
    A<=S(0);
    B<=S(1);
    C<=S(2);
    D<=S(3);

    Ands(1)<= B and D;
    Ands(2)<= not B and not D;
    Ands(3)<= C and D;
    Ands(4)<= not C and not D;
    Ands(5)<= C and not D;
    Ands(6)<= not B and C;
    Ands(7)<= B and not C and D;
    Ands(8)<= B and not C;
    Ands(9)<= B and not D;

    Z(0)<= A or C or Ands(1) or Ands(2);
    Z(1)<= not B or Ands(4) or Ands(3);
    Z(2)<= B or D or not C;
    Z(3)<= A or Ands(2) or Ands(7) or Ands(5) or Ands(6);
    Z(4)<= Ands(2) or Ands(5);
    Z(5)<= A or Ands(4) or Ands(8) or Ands(9);
    Z(6)<= A or Ands(5) or Ands(8) or Ands(6);

end arch;

Practice4/Multiplexor4_1.vhdl
entity Multiplexor4_1 is
    port(
        A: in bit_vector(3 downto 0);
        S: in bit_vector(1 downto 0);
        Z: out bit
    );
end entity;

architecture arch of Multiplexor4_1 is
signal notS: bit_vector(1 downto 0);
signal temp: bit_vector(3 downto 0);
begin
    notS(0)<= not S(0);
    notS(1)<= not S(1);
    temp(0)<=(A(0) and notS(0) and notS(1));
    temp(1)<=(A(1) and notS(1) and S(0));
    temp(2)<=(A(2) and notS(0) and S(1));
    temp(3)<=(A(3) and S(0) and S(1));
    Z<= (temp(0) or temp(1) or temp(2) or temp(3)); 
end arch;

Practice4/FF_JK.vhdl
entity FF_JK is
    port(
        CLK,J,K,PRESET,CLEAR,EN: in bit;
        Q,Qn: out bit
        );
end entity;
 
architecture arch of FF_JK is
    signal intQ: bit;
begin
    Q<=intQ;
    Qn<=not intQ;
    process(CLK,PRESET,CLEAR)
        begin

        if EN='0' then
            null;
        elsif CLEAR='0' then
            intQ<='0';
        elsif PRESET='0' then
            intQ<='1';
        elsif CLK'event and CLK='1' then
            if J = '0' and K = '0' then
                intQ <= intQ;
            elsif J = '0' and K = '1' then
                intQ <= '0';
            elsif J = '1' and K = '0' then
                intQ <= '1';
            else
                intQ <= not intQ;
            end if;
        end if;
    end process;
end arch;

Practice4/Counter2B.vhdl
entity Counter2B is
    port(
        CLK: in bit;
        CLEAR: in bit;
        PRESET: in bit;
        EN: in bit;
        Z: out bit_vector(1 downto 0)
        );
end Counter2B;
 
architecture arch of Counter2B is
    component FF_JK is
        port(
            CLK,J,K,PRESET,CLEAR,EN: in bit;
            Q,Qn: out bit
            );
    end component;
    signal intQ: bit_vector(1 downto 0);
    signal intQN: bit_vector(1 downto 0);
    signal intJK: bit_vector(1 downto 0);
begin
    intJK(0)<='1';
    intJK(1)<=intQ(0);
    F0: FF_JK port map(CLK=>CLK,J=>intJK(0),K=>intJK(0),PRESET=>PRESET,CLEAR=>CLEAR,Q=>intQ(0),Qn=>intQN(0),EN=>EN);
    F1: FF_JK port map(CLK=>CLK,J=>intJK(1),K=>intJK(1),PRESET=>PRESET,CLEAR=>CLEAR,Q=>intQ(1),Qn=>intQN(1),EN=>EN);
    Z(0)<=intQ(0);
    Z(1)<=intQ(1);
    
end arch;

Practice4/controller.vhdl
entity controller is
    port(
        CLK: in bit;
        CLEAR: in bit;
        A: in bit_vector(15 downto 0);
        D: in bit_vector(3 downto 0);
        --DP,G,F,E,D,C,B,A
        Z: out bit_vector(7 downto 0);
        E: out bit_vector(3 downto 0)
    );
end controller;

architecture arch of controller is
    component Counter2B is
        port(
            CLK: in bit;
            CLEAR: in bit;
            PRESET: in bit;
            EN: in bit;
            Z: out bit_vector(1 downto 0)
            );
    end component;
    component Multiplexor4_1 is
        port(
            A: in bit_vector(3 downto 0);
            S: in bit_vector(1 downto 0);
            Z: out bit
        );
    end component;
    component decoder7 is
        port(
            S:in bit_vector(3 downto 0);
            Z:out bit_vector(6 downto 0)
        );
    end component;
    signal Zint: bit_vector(1 downto 0);
    --4 BITS AND DECIMAL POINT
    signal Act: bit_vector(4 downto 0);
    --A-G
    signal ActD: bit_vector(6 downto 0);
begin
    FS0:Counter2B port map(CLK,CLEAR,'1','1',Zint);
    
    --Enables Displays
    E(0)<=not Zint(0) and not Zint(1);
    E(1)<=    Zint(0) and not Zint(1);
    E(2)<=not Zint(0) and     Zint(1);
    E(3)<=    Zint(0) and     Zint(1);
    
    --Multiplexing of bits
    MS0:Multiplexor4_1 port map( A(0)=>A(0) ,A(1)=>A(4), A(2)=>A(8) , A(3)=>A(12),S=>Zint,Z=>Act(3));
    MS1:Multiplexor4_1 port map( A(0)=>A(1) ,A(1)=>A(5), A(2)=>A(9) , A(3)=>A(13),S=>Zint,Z=>Act(2));
    MS2:Multiplexor4_1 port map( A(0)=>A(2) ,A(1)=>A(6), A(2)=>A(10), A(3)=>A(14),S=>Zint,Z=>Act(1));
    MS3:Multiplexor4_1 port map( A(0)=>A(3) ,A(1)=>A(7), A(2)=>A(11), A(3)=>A(15),S=>Zint,Z=>Act(0));
    MS4:Multiplexor4_1 port map( A(0)=>D(0) ,A(1)=>D(1), A(2)=>D(2),  A(3)=>D(3) ,S=>Zint,Z=>Act(4));
    
    --DECODER
    DS0:decoder7 port map(S(0)=>Act(0), S(1)=>Act(1), S(2)=>Act(2), S(3)=>Act(3),Z=>ActD);
    
    Z <= Act(4) & ActD;
    

end arch;

Practice4/controller_tb.vhdl
entity controller_tb is
end controller_tb;

architecture arch of controller_tb is
    component controller is
        port(
            CLK: in bit;
            CLEAR: in bit;
            A: in bit_vector(15 downto 0);
            D: in bit_vector(3 downto 0);
            --DP,G,F,E,D,C,B,A
            Z: out bit_vector(7 downto 0);
            E: out bit_vector(3 downto 0)
        );
    end component;
    signal CLK: bit;
    signal CLEAR: bit :='1';
    signal A: bit_vector(15 downto 0);
    signal D: bit_vector(3 downto 0);
    signal Z: bit_vector(7 downto 0);
    signal E: bit_vector(3 downto 0);
    
begin
    FS0: controller port map(CLK,CLEAR,A,D,Z,E);
    
    CLK_process : process
    begin
        wait for 5 ns;
        CLK<='0';
        wait for 5 ns;
        CLK<='1';
    end process;

    Set_process : process
    begin
        A<="1000000000000001";
        D<="0000";
        wait for 80 ns;
        A<="0010000110001001";
        D<="0010";
        wait for 40 ns;
        wait;
    end process;
    
end arch;

Practice4/controller_tb.vcd
$date
  Fri May  1 23:37:30 2020
$end
$version
  GHDL v0
$end
$timescale
  1 fs
$end
$scope module standard $end
$upscope $end
$scope module controller_tb $end
$var reg 1 ! clk $end
$var reg 1 " clear $end
$var reg 16 # a[15:0] $end
$var reg 4 $ d[3:0] $end
$var reg 8 % z[7:0] $end
$var reg 4 & e[3:0] $end
$scope module fs0 $end
$var reg 1 ' clk $end
$var reg 1 ( clear $end
$var reg 16 ) a[15:0] $end
$var reg 4 * d[3:0] $end
$var reg 8 + z[7:0] $end
$var reg 4 , e[3:0] $end
$var reg 2 - zint[1:0] $end
$var reg 5 . act[4:0] $end
$var reg 7 / actd[6:0] $end
$scope module fs0 $end
$var reg 1 0 clk $end
$var reg 1 1 clear $end
$var reg 1 2 preset $end
$var reg 1 3 en $end
$var reg 2 4 z[1:0] $end
$var reg 2 5 intq[1:0] $end
$var reg 2 6 intqn[1:0] $end
$var reg 2 7 intjk[1:0] $end
$scope module f0 $end
$var reg 1 8 clk $end
$var reg 1 9 j $end
$var reg 1 : k $end
$var reg 1 ; preset $end
$var reg 1 < clear $end
$var reg 1 = en $end
$var reg 1 > q $end
$var reg 1 ? qn $end
$var reg 1 @ intq $end
$upscope $end
$scope module f1 $end
$var reg 1 A clk $end
$var reg 1 B j $end
$var reg 1 C k $end
$var reg 1 D preset $end
$var reg 1 E clear $end
$var reg 1 F en $end
$var reg 1 G q $end
$var reg 1 H qn $end
$var reg 1 I intq $end
$upscope $end
$upscope $end
$scope module ms0 $end
$var reg 4 J a[3:0] $end
$var reg 2 K s[1:0] $end
$var reg 1 L z $end
$var reg 2 M nots[1:0] $end
$var reg 4 N temp[3:0] $end
$upscope $end
$scope module ms1 $end
$var reg 4 O a[3:0] $end
$var reg 2 P s[1:0] $end
$var reg 1 Q z $end
$var reg 2 R nots[1:0] $end
$var reg 4 S temp[3:0] $end
$upscope $end
$scope module ms2 $end
$var reg 4 T a[3:0] $end
$var reg 2 U s[1:0] $end
$var reg 1 V z $end
$var reg 2 W nots[1:0] $end
$var reg 4 X temp[3:0] $end
$upscope $end
$scope module ms3 $end
$var reg 4 Y a[3:0] $end
$var reg 2 Z s[1:0] $end
$var reg 1 [ z $end
$var reg 2 \ nots[1:0] $end
$var reg 4 ] temp[3:0] $end
$upscope $end
$scope module ms4 $end
$var reg 4 ^ a[3:0] $end
$var reg 2 _ s[1:0] $end
$var reg 1 ` z $end
$var reg 2 a nots[1:0] $end
$var reg 4 b temp[3:0] $end
$upscope $end
$scope module ds0 $end
$var reg 4 c s[3:0] $end
$var reg 7 d z[6:0] $end
$var reg 9 e ands[9:1] $end
$var reg 1 f a $end
$var reg 1 g b $end
$var reg 1 h c $end
$var reg 1 i d $end
$upscope $end
$upscope $end
$upscope $end
$enddefinitions $end
#0
0!
1"
b1000000000000001 #
b0000 $
b00000110 %
b0001 &
0'
1(
b1000000000000001 )
b0000 *
b00000110 +
b0001 ,
b00 -
b01000 .
b0000110 /
00
11
12
13
b00 4
b00 5
b11 6
b01 7
08
19
1:
1;
1<
1=
0>
1?
0@
0A
0B
0C
1D
1E
1F
0G
1H
0I
b0001 J
b00 K
1L
b11 M
b0001 N
b0000 O
b00 P
0Q
b11 R
b0000 S
b0000 T
b00 U
0V
b11 W
b0000 X
b1000 Y
b00 Z
0[
b11 \
b0000 ]
b0000 ^
b00 _
0`
b11 a
b0000 b
b1000 c
b0000110 d
b000000000 e
0f
0g
0h
1i
#5000000
#10000000
1!
b00111111 %
b0010 &
1'
b00111111 +
b0010 ,
b01 -
b00000 .
b0111111 /
10
b01 4
b01 5
b10 6
b11 7
18
1>
0?
1@
1A
1B
1C
b01 K
0L
b10 M
b0000 N
b01 P
b10 R
b01 U
b10 W
b01 Z
b10 \
b01 _
b10 a
b0000 c
b0111111 d
b000001010 e
0i
#15000000
0!
0'
00
08
0A
#20000000
1!
b0100 &
1'
b0100 ,
b10 -
10
b10 4
b10 5
b01 6
b01 7
18
0>
1?
0@
1A
0B
0C
1G
0H
1I
b10 K
b01 M
b10 P
b01 R
b10 U
b01 W
b10 Z
b01 \
b10 _
b01 a
#25000000
0!
0'
00
08
0A
#30000000
1!
b01111111 %
b1000 &
1'
b01111111 +
b1000 ,
b11 -
b00001 .
b1111111 /
10
b11 4
b11 5
b00 6
b11 7
18
1>
0?
1@
1A
1B
1C
b11 K
b00 M
b11 P
b00 R
b11 U
b00 W
b11 Z
1[
b00 \
b1000 ]
b11 _
b00 a
b0001 c
b1111111 d
1f
#35000000
0!
0'
00
08
0A
#40000000
1!
b00000110 %
b0001 &
1'
b00000110 +
b0001 ,
b00 -
b01000 .
b0000110 /
10
b00 4
b00 5
b11 6
b01 7
18
0>
1?
0@
1A
0B
0C
0G
1H
0I
b00 K
1L
b11 M
b0001 N
b00 P
b11 R
b00 U
b11 W
b00 Z
0[
b11 \
b0000 ]
b00 _
b11 a
b1000 c
b0000110 d
b000000000 e
0f
1i
#45000000
0!
0'
00
08
0A
#50000000
1!
b00111111 %
b0010 &
1'
b00111111 +
b0010 ,
b01 -
b00000 .
b0111111 /
10
b01 4
b01 5
b10 6
b11 7
18
1>
0?
1@
1A
1B
1C
b01 K
0L
b10 M
b0000 N
b01 P
b10 R
b01 U
b10 W
b01 Z
b10 \
b01 _
b10 a
b0000 c
b0111111 d
b000001010 e
0i
#55000000
0!
0'
00
08
0A
#60000000
1!
b0100 &
1'
b0100 ,
b10 -
10
b10 4
b10 5
b01 6
b01 7
18
0>
1?
0@
1A
0B
0C
1G
0H
1I
b10 K
b01 M
b10 P
b01 R
b10 U
b01 W
b10 Z
b01 \
b10 _
b01 a
#65000000
0!
0'
00
08
0A
#70000000
1!
b01111111 %
b1000 &
1'
b01111111 +
b1000 ,
b11 -
b00001 .
b1111111 /
10
b11 4
b11 5
b00 6
b11 7
18
1>
0?
1@
1A
1B
1C
b11 K
b00 M
b11 P
b00 R
b11 U
b00 W
b11 Z
1[
b00 \
b1000 ]
b11 _
b00 a
b0001 c
b1111111 d
1f
#75000000
0!
0'
00
08
0A
#80000000
1!
b0010000110001001 #
b0010 $
b01101111 %
b0001 &
1'
b0010000110001001 )
b0010 *
b01101111 +
b0001 ,
b00 -
b01001 .
b1101111 /
10
b00 4
b00 5
b11 6
b01 7
18
0>
1?
0@
1A
0B
0C
0G
1H
0I
b0101 J
b00 K
1L
b11 M
b0001 N
b1000 O
b00 P
0Q
b11 R
b0000 S
b00 U
b11 W
b0011 Y
b00 Z
1[
b11 \
b0001 ]
b0010 ^
b00 _
b11 a
b1001 c
b1101111 d
b000000000 e
1f
0h
1i
#85000000
0!
0'
00
08
0A
#90000000
1!
b11111111 %
b0010 &
1'
b11111111 +
b0010 ,
b01 -
b10001 .
b1111111 /
10
b01 4
b01 5
b10 6
b11 7
18
1>
0?
1@
1A
1B
1C
b01 K
0L
b10 M
b0000 N
b01 P
b10 R
b01 U
b10 W
b01 Z
b10 \
b0010 ]
b01 _
1`
b10 a
b0010 b
b0001 c
b1111111 d
b000001010 e
0i
#95000000
0!
0'
00
08
0A
#100000000
1!
b00000110 %
b0100 &
1'
b00000110 +
b0100 ,
b10 -
b01000 .
b0000110 /
10
b10 4
b10 5
b01 6
b01 7
18
0>
1?
0@
1A
0B
0C
1G
0H
1I
b10 K
1L
b01 M
b0100 N
b10 P
b01 R
b10 U
b01 W
b10 Z
0[
b01 \
b0000 ]
b10 _
0`
b01 a
b0000 b
b1000 c
b0000110 d
b000000000 e
0f
1i
#105000000
0!
0'
00
08
0A
#110000000
1!
b01011011 %
b1000 &
1'
b01011011 +
b1000 ,
b11 -
b00100 .
b1011011 /
10
b11 4
b11 5
b00 6
b11 7
18
1>
0?
1@
1A
1B
1C
b11 K
0L
b00 M
b0000 N
b11 P
1Q
b00 R
b1000 S
b11 U
b00 W
b11 Z
b00 \
b11 _
b00 a
b0100 c
b1011011 d
b000110010 e
1h
0i
#115000000
0!
0'
00
08
0A
#120000000
1!
b01101111 %
b0001 &
1'
b01101111 +
b0001 ,
b00 -
b01001 .
b1101111 /
10
b00 4
b00 5
b11 6
b01 7
18
0>
1?
0@
1A
0B
0C
0G
1H
0I
b00 K
1L
b11 M
b0001 N
b00 P
0Q
b11 R
b0000 S
b00 U
b11 W
b00 Z
1[
b11 \
b0001 ]
b00 _
b11 a
b1001 c
b1101111 d
b000000000 e
1f
0h
1i
#125000000
0!
0'
00
08
0A
#130000000
1!
b11111111 %
b0010 &
1'
b11111111 +
b0010 ,
b01 -
b10001 .
b1111111 /
10
b01 4
b01 5
b10 6
b11 7
18
1>
0?
1@
1A
1B
1C
b01 K
0L
b10 M
b0000 N
b01 P
b10 R
b01 U
b10 W
b01 Z
b10 \
b0010 ]
b01 _
1`
b10 a
b0010 b
b0001 c
b1111111 d
b000001010 e
0i
#135000000
0!
0'
00
08
0A
#140000000
1!
b00000110 %
b0100 &
1'
b00000110 +
b0100 ,
b10 -
b01000 .
b0000110 /
10
b10 4
b10 5
b01 6
b01 7
18
0>
1?
0@
1A
0B
0C
1G
0H
1I
b10 K
1L
b01 M
b0100 N
b10 P
b01 R
b10 U
b01 W
b10 Z
0[
b01 \
b0000 ]
b10 _
0`
b01 a
b0000 b
b1000 c
b0000110 d
b000000000 e
0f
1i
#145000000
0!
0'
00
08
0A
#150000000
1!
b01011011 %
b1000 &
1'
b01011011 +
b1000 ,
b11 -
b00100 .
b1011011 /
10
b11 4
b11 5
b00 6
b11 7
18
1>
0?
1@
1A
1B
1C
b11 K
0L
b00 M
b0000 N
b11 P
1Q
b00 R
b1000 S
b11 U
b00 W
b11 Z
b00 \
b11 _
b00 a
b0100 c
b1011011 d
b000110010 e
1h
0i
#155000000
0!
0'
00
08
0A
#160000000
1!
b01101111 %
b0001 &
1'
b01101111 +
b0001 ,
b00 -
b01001 .
b1101111 /
10
b00 4
b00 5
b11 6
b01 7
18
0>
1?
0@
1A
0B
0C
0G
1H
0I
b00 K
1L
b11 M
b0001 N
b00 P
0Q
b11 R
b0000 S
b00 U
b11 W
b00 Z
1[
b11 \
b0001 ]
b00 _
b11 a
b1001 c
b1101111 d
b000000000 e
1f
0h
1i
#165000000
0!
0'
00
08
0A
#170000000
1!
b11111111 %
b0010 &
1'
b11111111 +
b0010 ,
b01 -
b10001 .
b1111111 /
10
b01 4
b01 5
b10 6
b11 7
18
1>
0?
1@
1A
1B
1C
b01 K
0L
b10 M
b0000 N
b01 P
b10 R
b01 U
b10 W
b01 Z
b10 \
b0010 ]
b01 _
1`
b10 a
b0010 b
b0001 c
b1111111 d
b000001010 e
0i
#175000000
0!
0'
00
08
0A
#180000000
1!
b00000110 %
b0100 &
1'
b00000110 +
b0100 ,
b10 -
b01000 .
b0000110 /
10
b10 4
b10 5
b01 6
b01 7
18
0>
1?
0@
1A
0B
0C
1G
0H
1I
b10 K
1L
b01 M
b0100 N
b10 P
b01 R
b10 U
b01 W
b10 Z
0[
b01 \
b0000 ]
b10 _
0`
b01 a
b0000 b
b1000 c
b0000110 d
b000000000 e
0f
1i
#185000000
0!
0'
00
08
0A
#190000000
1!
b01011011 %
b1000 &
1'
b01011011 +
b1000 ,
b11 -
b00100 .
b1011011 /
10
b11 4
b11 5
b00 6
b11 7
18
1>
0?
1@
1A
1B
1C
b11 K
0L
b00 M
b0000 N
b11 P
1Q
b00 R
b1000 S
b11 U
b00 W
b11 Z
b00 \
b11 _
b00 a
b0100 c
b1011011 d
b000110010 e
1h
0i
#195000000
0!
0'
00
08
0A
#200000000
1!
b01101111 %
b0001 &
1'
b01101111 +
b0001 ,
b00 -
b01001 .
b1101111 /
10
b00 4
b00 5
b11 6
b01 7
18
0>
1?
0@
1A
0B
0C
0G
1H
0I
b00 K
1L
b11 M
b0001 N
b00 P
0Q
b11 R
b0000 S
b00 U
b11 W
b00 Z
1[
b11 \
b0001 ]
b00 _
b11 a
b1001 c
b1101111 d
b000000000 e
1f
0h
1i
