LCDCONTROLLER/LCD.vhdl
library ieee;
use ieee.std_logic_1164.all;
use ieee.std_logic_textio.all;
library std;
use std.textio.all;
library IEEE;
use IEEE.numeric_bit.all;

entity lcd is
    port(
        clk,reset,rs,rw : in bit;
        dataIn : in bit_vector(7 downto 0);
        rsOut,rwOut,en : out bit;
        dataOut : out bit_vector(7 downto 0)
    );
end lcd;

architecture arch of lcd is
    file fout : TEXT open WRITE_MODE is "output.txt";
    signal state : integer range 1 to 6 := 1;
begin
    en <= clk;
    init : process(state)
    variable current_line : line;
    begin
        case(state) is 
        when 1 =>
            rsOut <= '0';
            rwOut <= '0';
            dataOut <= x"01";
            write(current_line, string'("instr(0x01);"));
        when 2 =>
            rsOut <= '0';
            rwOut <= '0';
            dataOut <= x"38";
            write(current_line, string'("instr(0x38);"));
        when 3 =>
            rsOut <= '0';
            rwOut <= '0';
            dataOut <= x"0F";
            write(current_line, string'("instr(0x0F);"));
        when 4 =>
            rsOut <= '0';
            rwOut <= '0';
            dataOut <= x"06";
            write(current_line, string'("instr(0x06);"));
        when 5|6 =>
            rsOut <= rs;
            rwOut <= rw;
            dataOut <= dataIn;
            if rs = '0' then
                write(current_line, string'("instr("));
            else 
                write(current_line, string'("data("));
            end if;
            write(current_line, TO_INTEGER(unsigned(dataIn)));
            write(current_line, string'(");"));
        end case;
        writeLine(fout,current_line);
    end process;

    clkP : process(clk)
    begin
        if clk'event and clk='0' then
            if state < 5 then
                state <= state + 1;
            elsif reset = '0' then
                state <= 1;
            elsif state = 5 then
                state <= state + 1;
            elsif state = 6 then
                state <= 5;
            end if;
        end if;
    end process;

end arch;
--ghdl -a --ieee=synopsys  LCD.vhdl && ghdl -e --ieee=synopsys  LCD

LCDCONTROLLER/LCD_tb.vhdl
library ieee;
use ieee.std_logic_1164.all;
use ieee.std_logic_textio.all;
library std;
use std.textio.all;

entity LCD_tb is
end LCD_tb;

architecture arch of LCD_tb is
    component lcd is
        port(
            clk,reset,rs,rw : in bit;
            dataIn : in bit_vector(7 downto 0);
            rsOut,rwOut,en : out bit;
            dataOut : out bit_vector(7 downto 0)
        );
    end component;
    signal clk,reset,rs,rw : bit := '0';
    signal dataIn : bit_vector(7 downto 0);
    signal rsOut,rwOut,en : bit;
    signal dataOut : bit_vector(7 downto 0);
begin
    F0: LCD port map(clk,reset,rs,rw,dataIn,rsOut,rwOut,en,dataOut);
    stimulus : process
        file fin : TEXT open READ_MODE is "input.txt";
        variable current_read_line : line;
        variable field_rs : bit;
        variable field_rw : bit;
        variable field_dataIn : bit_vector(7 downto 0);
        variable field_reset : bit;
    begin
        reset <= '1';
        wait for 15 ns;
        readline(fin,current_read_line);
        while (not endfile(fin)) loop
            readline(fin,current_read_line);
            read(current_read_line, field_rs);
            read(current_read_line, field_rw);
            read(current_read_line, field_dataIn);
            read(current_read_line, field_reset);
            rs <= field_rs;
            rw <= field_rw;
            dataIn <= field_dataIn;
            reset <= field_reset;
            wait for 5 ns;
        end loop ; 
        wait;
    end process;

    clkP : process
    begin
        clk <= not clk;
        wait for 2.5 ns;
    end process;

end arch;
--ghdl -a --ieee=synopsys  LCD_tb.vhdl && ghdl -e --ieee=synopsys  LCD_tb

LCDCONTROLLER/LCD_tb.vcd
$date
  Tue May 12 16:58:33 2020
$end
$version
  GHDL v0
$end
$timescale
  1 fs
$end
$scope module standard $end
$upscope $end
$scope module std_logic_1164 $end
$upscope $end
$scope module textio $end
$upscope $end
$scope module std_logic_textio $end
$upscope $end
$scope module numeric_bit $end
$upscope $end
$scope module lcd_tb $end
$var reg 1 ! clk $end
$var reg 1 " reset $end
$var reg 1 # rs $end
$var reg 1 $ rw $end
$var reg 8 % datain[7:0] $end
$var reg 1 & rsout $end
$var reg 1 ' rwout $end
$var reg 1 ( en $end
$var reg 8 ) dataout[7:0] $end
$scope module f0 $end
$var reg 1 * clk $end
$var reg 1 + reset $end
$var reg 1 , rs $end
$var reg 1 - rw $end
$var reg 8 . datain[7:0] $end
$var reg 1 / rsout $end
$var reg 1 0 rwout $end
$var reg 1 1 en $end
$var reg 8 2 dataout[7:0] $end
$var integer 32 3 state $end
$upscope $end
$upscope $end
$enddefinitions $end
#0
1!
1"
0#
0$
b00000000 %
0&
0'
1(
b00000001 )
1*
1+
0,
0-
b00000000 .
0/
00
11
b00000001 2
b1 3
#2500000
0!
0(
b00111000 )
0*
01
b00111000 2
b10 3
#5000000
1!
1(
1*
11
#7500000
0!
0(
b00001111 )
0*
01
b00001111 2
b11 3
#10000000
1!
1(
1*
11
#12500000
0!
0(
b00000110 )
0*
01
b00000110 2
b100 3
#15000000
1!
1#
b01001010 %
1(
1*
1,
b01001010 .
11
#17500000
0!
1&
0(
b01001010 )
0*
1/
01
b01001010 2
b101 3
#20000000
1!
b01001111 %
1(
1*
b01001111 .
11
#22500000
0!
0(
b01001111 )
0*
01
b01001111 2
b110 3
#25000000
1!
b01010011 %
1(
1*
b01010011 .
11
#27500000
0!
0(
b01010011 )
0*
01
b01010011 2
b101 3
#30000000
1!
b01000101 %
1(
1*
b01000101 .
11
#32500000
0!
0(
b01000101 )
0*
01
b01000101 2
b110 3
#35000000
1!
0#
b11000000 %
1(
1*
0,
b11000000 .
11
#37500000
0!
0&
0(
b11000000 )
0*
0/
01
b11000000 2
b101 3
#40000000
1!
1#
b01000011 %
1(
1*
1,
b01000011 .
11
#42500000
0!
1&
0(
b01000011 )
0*
1/
01
b01000011 2
b110 3
#45000000
1!
b01001001 %
1(
1*
b01001001 .
11
#47500000
0!
0(
b01001001 )
0*
01
b01001001 2
b101 3
#50000000
1!
b01010011 %
1(
1*
b01010011 .
11
#52500000
0!
0(
b01010011 )
0*
01
b01010011 2
b110 3
#55000000
1!
b01001110 %
1(
1*
b01001110 .
11
#57500000
0!
0(
b01001110 )
0*
01
b01001110 2
b101 3
#60000000
1!
b01000101 %
1(
1*
b01000101 .
11
#62500000
0!
0(
b01000101 )
0*
01
b01000101 2
b110 3
#65000000
1!
b01010010 %
1(
1*
b01010010 .
11
#67500000
0!
0(
b01010010 )
0*
01
b01010010 2
b101 3
#70000000
1!
b01001111 %
1(
1*
b01001111 .
11
#72500000
0!
0(
b01001111 )
0*
01
b01001111 2
b110 3
#75000000
1!
b01010011 %
1(
1*
b01010011 .
11
#77500000
0!
0(
b01010011 )
0*
01
b01010011 2
b101 3
#80000000
1!
0"
0#
b00000001 %
1(
1*
0+
0,
b00000001 .
11
#82500000
0!
0&
0(
b00000001 )
0*
0/
01
b00000001 2
b1 3
#85000000
1!
1"
1#
1$
1(
1*
1+
1,
1-
11
#87500000
0!
0(
b00111000 )
0*
01
b00111000 2
b10 3
#90000000
1!
1(
1*
11
#92500000
0!
0(
b00001111 )
0*
01
b00001111 2
b11 3
#95000000
1!
1(
1*
11
#97500000
0!
0(
b00000110 )
0*
01
b00000110 2
b100 3
#100000000
1!
0$
b01001010 %
1(
1*
0-
b01001010 .
11
#102500000
0!
1&
0(
b01001010 )
0*
1/
01
b01001010 2
b101 3
#105000000
1!
b01001111 %
1(
1*
b01001111 .
11
#107500000
0!
0(
b01001111 )
0*
01
b01001111 2
b110 3
#110000000
1!
b01010011 %
1(
1*
b01010011 .
11
#112500000
0!
0(
b01010011 )
0*
01
b01010011 2
b101 3
#115000000
1!
b01000101 %
1(
1*
b01000101 .
11
#117500000
0!
0(
b01000101 )
0*
01
b01000101 2
b110 3
#120000000
1!
0#
b11000000 %
1(
1*
0,
b11000000 .
11
#122500000
0!
0&
0(
b11000000 )
0*
0/
01
b11000000 2
b101 3
#125000000
1!
1#
b01000011 %
1(
1*
1,
b01000011 .
11
#127500000
0!
1&
0(
b01000011 )
0*
1/
01
b01000011 2
b110 3
#130000000
1!
b01001001 %
1(
1*
b01001001 .
11
#132500000
0!
0(
b01001001 )
0*
01
b01001001 2
b101 3
#135000000
1!
b01010011 %
1(
1*
b01010011 .
11
#137500000
0!
0(
b01010011 )
0*
01
b01010011 2
b110 3
#140000000
1!
b01001110 %
1(
1*
b01001110 .
11
#142500000
0!
0(
b01001110 )
0*
01
b01001110 2
b101 3
#145000000
1!
b01000101 %
1(
1*
b01000101 .
11
#147500000
0!
0(
b01000101 )
0*
01
b01000101 2
b110 3
#150000000
1!
b01010010 %
1(
1*
b01010010 .
11
#152500000
0!
0(
b01010010 )
0*
01
b01010010 2
b101 3
#155000000
1!
b01001111 %
1(
1*
b01001111 .
11
#157500000
0!
0(
b01001111 )
0*
01
b01001111 2
b110 3
#160000000
1!
b01010011 %
1(
1*
b01010011 .
11
#162500000
0!
0(
b01010011 )
0*
01
b01010011 2
b101 3
#165000000
1!
1(
1*
11
#167500000
0!
0(
0*
01
b110 3
#170000000
1!
1(
1*
11
#172500000
0!
0(
0*
01
b101 3
#175000000
1!
1(
1*
11
