Practice4/FF_JK.vhdl
entity FF_JK is
    port(
        CLK,J,K,PRESET,CLEAR,EN: in bit;
        Q,Qn: out bit
        );
end entity;
 
architecture arch of FF_JK is
    signal intQ: bit;
begin
    Q<=intQ;
    Qn<=not intQ;
    process(CLK,PRESET,CLEAR)
        begin

        if EN='0' then
            null;
        elsif CLEAR='0' then
            intQ<='0';
        elsif PRESET='0' then
            intQ<='1';
        elsif CLK'event and CLK='1' then
            if J = '0' and K = '0' then
                intQ <= intQ;
            elsif J = '0' and K = '1' then
                intQ <= '0';
            elsif J = '1' and K = '0' then
                intQ <= '1';
            else
                intQ <= not intQ;
            end if;
        end if;
    end process;
end arch;

Practice3/Counter4B.vhdl
entity Counter4B is
    port(
        CLK: in bit;
        CLEAR: in bit;
        PRESET: in bit;
        EN: in bit;
        Z: out bit_vector(3 downto 0)
        );
end Counter4B;
 
architecture arch of Counter4B is
    component FF_JK is
        port(
            CLK,J,K,PRESET,CLEAR,EN: in bit;
            Q,Qn: out bit
            );
    end component;
    signal intQ: bit_vector(3 downto 0);
    signal intJK: bit_vector(3 downto 0);
    signal intQN: bit_vector(3 downto 0);
begin
    intJK(0)<='1';
    intJK(1)<=intQ(0);
    intJK(2)<=intQ(0) and intQ(1);
    intJK(3)<=intJK(2) and intQ(2);
    F0: FF_JK port map(CLK=>CLK,J=>intJK(0),K=>intJK(0),PRESET=>PRESET,CLEAR=>CLEAR,Q=>intQ(0),Qn=>intQN(0),EN=>EN);
    F1: FF_JK port map(CLK=>CLK,J=>intJK(1),K=>intJK(1),PRESET=>PRESET,CLEAR=>CLEAR,Q=>intQ(1),Qn=>intQN(1),EN=>EN);
    F2: FF_JK port map(CLK=>CLK,J=>intJK(2),K=>intJK(2),PRESET=>PRESET,CLEAR=>CLEAR,Q=>intQ(2),Qn=>intQN(2),EN=>EN);
    F3: FF_JK port map(CLK=>CLK,J=>intJK(3),K=>intJK(3),PRESET=>PRESET,CLEAR=>CLEAR,Q=>intQ(3),Qn=>intQN(3),EN=>EN);
    Z(0)<=intQ(0);
    Z(1)<=intQ(1);
    Z(2)<=intQ(2);
    Z(3)<=intQ(3);
    
end arch;

Practice3/Counter4B_tb.vhdl
entity Counter4B_tb is
end Counter4B_tb;
 
architecture arch of Counter4B_tb is
    component Counter4B is
        port(
            CLK: in bit;     
            CLEAR: in bit;
            PRESET: in bit;
            EN: in bit;
            Z: out bit_vector(3 downto 0)
            );
    end component;
    signal CLK: bit := '0';
    signal CLEAR: bit := '1';
    signal PRESET: bit := '1';
    signal EN: bit := '1';
    signal Z: bit_vector(3 downto 0);
begin
    FS0: Counter4B port map(CLK,CLEAR,PRESET,EN,Z);
    CLK_process : process
    begin
        CLK<='0';
        wait for 5 ns;
        CLK<='1';
        wait for 5 ns;
    end process;

    Set_process : process
    begin
        CLEAR<='0';
        wait for 5 ns;
        CLEAR<='1';
        wait;
    end process;
end arch;

Practice3/Counter4B_tb.vcd
$date
  Mon Mar 30 15:30:48 2020
$end
$version
  GHDL v0
$end
$timescale
  1 fs
$end
$scope module standard $end
$upscope $end
$scope module counter4b_tb $end
$var reg 1 ! clk $end
$var reg 1 " clear $end
$var reg 1 # preset $end
$var reg 1 $ en $end
$var reg 4 % z[3:0] $end
$scope module fs0 $end
$var reg 1 & clk $end
$var reg 1 ' clear $end
$var reg 1 ( preset $end
$var reg 1 ) en $end
$var reg 4 * z[3:0] $end
$var reg 4 + intq[3:0] $end
$var reg 4 , intjk[3:0] $end
$var reg 4 - intqn[3:0] $end
$scope module f0 $end
$var reg 1 . clk $end
$var reg 1 / j $end
$var reg 1 0 k $end
$var reg 1 1 preset $end
$var reg 1 2 clear $end
$var reg 1 3 en $end
$var reg 1 4 q $end
$var reg 1 5 qn $end
$var reg 1 6 intq $end
$upscope $end
$scope module f1 $end
$var reg 1 7 clk $end
$var reg 1 8 j $end
$var reg 1 9 k $end
$var reg 1 : preset $end
$var reg 1 ; clear $end
$var reg 1 < en $end
$var reg 1 = q $end
$var reg 1 > qn $end
$var reg 1 ? intq $end
$upscope $end
$scope module f2 $end
$var reg 1 @ clk $end
$var reg 1 A j $end
$var reg 1 B k $end
$var reg 1 C preset $end
$var reg 1 D clear $end
$var reg 1 E en $end
$var reg 1 F q $end
$var reg 1 G qn $end
$var reg 1 H intq $end
$upscope $end
$scope module f3 $end
$var reg 1 I clk $end
$var reg 1 J j $end
$var reg 1 K k $end
$var reg 1 L preset $end
$var reg 1 M clear $end
$var reg 1 N en $end
$var reg 1 O q $end
$var reg 1 P qn $end
$var reg 1 Q intq $end
$upscope $end
$upscope $end
$upscope $end
$enddefinitions $end
#0
0!
0"
1#
1$
b0000 %
0&
0'
1(
1)
b0000 *
b0000 +
b0001 ,
b1111 -
0.
1/
10
11
02
13
04
15
06
07
08
09
1:
0;
1<
0=
1>
0?
0@
0A
0B
1C
0D
1E
0F
1G
0H
0I
0J
0K
1L
0M
1N
0O
1P
0Q
#5000000
1!
1"
b0001 %
1&
1'
b0001 *
b0001 +
b0011 ,
b1110 -
1.
12
14
05
16
17
18
19
1;
1@
1D
1I
1M
#10000000
0!
0&
0.
07
0@
0I
#15000000
1!
b0010 %
1&
b0010 *
b0010 +
b0001 ,
b1101 -
1.
04
15
06
17
08
09
1=
0>
1?
1@
1I
#20000000
0!
0&
0.
07
0@
0I
#25000000
1!
b0011 %
1&
b0011 *
b0011 +
b0111 ,
b1100 -
1.
14
05
16
17
18
19
1@
1A
1B
1I
#30000000
0!
0&
0.
07
0@
0I
#35000000
1!
b0100 %
1&
b0100 *
b0100 +
b0001 ,
b1011 -
1.
04
15
06
17
08
09
0=
1>
0?
1@
0A
0B
1F
0G
1H
1I
0J
0K
#40000000
0!
0&
0.
07
0@
0I
#45000000
1!
b0101 %
1&
b0101 *
b0101 +
b0011 ,
b1010 -
1.
14
05
16
17
18
19
1@
1I
#50000000
0!
0&
0.
07
0@
0I
#55000000
1!
b0110 %
1&
b0110 *
b0110 +
b0001 ,
b1001 -
1.
04
15
06
17
08
09
1=
0>
1?
1@
1I
#60000000
0!
0&
0.
07
0@
0I
#65000000
1!
b0111 %
1&
b0111 *
b0111 +
b1111 ,
b1000 -
1.
14
05
16
17
18
19
1@
1A
1B
1I
1J
1K
#70000000
0!
0&
0.
07
0@
0I
#75000000
1!
b1000 %
1&
b1000 *
b1000 +
b0001 ,
b0111 -
1.
04
15
06
17
08
09
0=
1>
0?
1@
0A
0B
0F
1G
0H
1I
0J
0K
1O
0P
1Q
#80000000
0!
0&
0.
07
0@
0I
#85000000
1!
b1001 %
1&
b1001 *
b1001 +
b0011 ,
b0110 -
1.
14
05
16
17
18
19
1@
1I
#90000000
0!
0&
0.
07
0@
0I
#95000000
1!
b1010 %
1&
b1010 *
b1010 +
b0001 ,
b0101 -
1.
04
15
06
17
08
09
1=
0>
1?
1@
1I
#100000000
0!
0&
0.
07
0@
0I
#105000000
1!
b1011 %
1&
b1011 *
b1011 +
b0111 ,
b0100 -
1.
14
05
16
17
18
19
1@
1A
1B
1I
#110000000
0!
0&
0.
07
0@
0I
#115000000
1!
b1100 %
1&
b1100 *
b1100 +
b0001 ,
b0011 -
1.
04
15
06
17
08
09
0=
1>
0?
1@
0A
0B
1F
0G
1H
1I
0J
0K
