Practice_GDC_CALCULATOR/ffd.vhdl
library ieee;
use ieee.std_logic_1164.all;

entity ffd is
    port (
        clk, ld, d: in std_logic;
        reset : in std_logic;
        q : out std_logic
    );
end entity;

architecture arch of ffd is
begin
    process (clk, reset)
    begin
        if (reset = '1') then
            q <= '0';
        elsif rising_edge(clk) then
            if ld = '1' then
                q <= d;
            end if;
        end if;
    end process;
    
end arch;

Practice_GDC_CALCULATOR/register4bits.vhdl
library ieee;
use ieee.std_logic_1164.all;

entity register4bits is 
    port(
        d_in : in std_logic_vector(3 downto 0);
        clk, ld , reset : in std_logic;
        d_out : out std_logic_vector(3 downto 0)
    );
end register4bits;

architecture arch of register4bits is
    component ffd is
        port (
            clk, ld, d: in std_logic;
            reset : in std_logic;
            q : out std_logic
        );
    end component;
begin
    
    ff_d0 : ffd port map (clk, ld, d_in(0),reset, d_out(0));
    ff_d1 : ffd port map (clk, ld, d_in(1),reset, d_out(1));
    ff_d2 : ffd port map (clk, ld, d_in(2),reset, d_out(2));
    ff_d3 : ffd port map (clk, ld, d_in(3),reset, d_out(3));

end arch;

Practice_GDC_CALCULATOR/substractor4bits.vhdl
library ieee;
use ieee.std_logic_1164.all;
library IEEE;
use IEEE.numeric_std.all;

entity substractor4bits is
    port(
        en     : in std_logic; 
        a, b   : in std_logic_vector(3 downto 0);
        d  : out std_logic_vector(3 downto 0)
    );
end entity;

architecture arch of substractor4bits is
    
begin
    d <= a when en='0' else std_logic_vector(unsigned(a)-unsigned(b));
end arch;

Practice_GDC_CALCULATOR/comparator.vhdl
library ieee;
use ieee.std_logic_1164.all;

entity comparator is
    port(
        x, y : in std_logic_vector(3 downto 0);
        x_gt_y, x_eq_y, x_lt_y : out std_logic
    );
end entity;

architecture arch of comparator is

begin
    
    x_gt_y <= '1' when x > y else '0';
    x_eq_y <= '1' when x = y else '0';
    x_lt_y <= '1' when x < y else '0';

end arch ;

Practice_GDC_CALCULATOR/mux.vhdl
library ieee;
use ieee.std_logic_1164.all;

entity mux is
    port(
        x,y : in std_logic_vector(3 downto 0);
        sel : in std_logic;
        res : out std_logic_vector(3 downto 0)
    );
end entity mux;

architecture arch of mux is
begin
    res <= x when sel ='0' else y;
end arch;

Practice_GDC_CALCULATOR/datapath.vhdl
library ieee;
use ieee.std_logic_1164.all;

entity datapath is
    port(
        x,y : in std_logic_vector(3 downto 0);
        x_sel,y_sel : in std_logic;
        clk : in std_logic;
        x_load,y_load,x_reset,y_reset : in std_logic;
        x_sub,y_sub : in std_logic;
        o_enb,o_reset : in std_logic;
        x_gt_y, x_eq_y, x_lt_y : out std_logic;
        z : out std_logic_vector(3 downto 0)
    );
end datapath;

architecture arch of datapath is
    component mux is
        port(
            x,y : in std_logic_vector(3 downto 0);
            sel : in std_logic;
            res : out std_logic_vector(3 downto 0)
        );
    end component;
    component register4bits is 
    port(
        d_in : in std_logic_vector(3 downto 0);
        clk, ld , reset : in std_logic;
        d_out : out std_logic_vector(3 downto 0)
    );
    end component;
    component substractor4bits is
        port(
            en     : in std_logic; 
            a, b   : in std_logic_vector(3 downto 0);
            d  : out std_logic_vector(3 downto 0)
        );
    end component;
    component comparator is
        port(
            x, y : in std_logic_vector(3 downto 0);
            x_gt_y, x_eq_y, x_lt_y : out std_logic
        );
    end component;
    signal xNew,yNew : std_logic_vector(3 downto 0) := "0000";
    signal inRx,inRy : std_logic_vector(3 downto 0) := "0000";
    signal outRx,outRy : std_logic_vector(3 downto 0) := "0000";
begin
    MUXx : mux port map(x,xNew,x_sel,inRx);
    MUXy : mux port map(y,yNew,y_sel,inRy);
    REGx : register4bits port map(inRx,clk,x_load,x_reset,outRx);
    REGy : register4bits port map(inRy,clk,y_load,y_reset,outRy);
    Cxy  : comparator port map(outRx,outRy, x_gt_y, x_eq_y, x_lt_y); 
    SUBx  : substractor4bits port map(x_sub,outRx,outRy,xNew);
    SUBy  : substractor4bits port map(y_sub,outRy,outRx,yNew);
    OUTR : register4bits port map(outRx,clk,o_enb,o_reset,z);
end arch;

Practice_GDC_CALCULATOR/controller.vhdl
library ieee;
use ieee.std_logic_1164.all;

entity controller is
    port(
        clk,reset: in std_logic;
        x_gt_y,x_eq_y,x_lt_y : in std_logic;
        x_sel,y_sel : out std_logic;
        x_reset,y_reset : out std_logic;
        x_load,y_load : out std_logic;
        x_sub,y_sub : out std_logic;
        o_enb,o_reset : out std_logic
    );
end controller;

architecture arch of controller is
    signal state : integer range 1 to 8 := 1;
begin
    combinational : process(state)
    begin
        case(state) is
            when 1 =>
                x_sel <= '0';
                y_sel <= '0';
                x_load<= '0';
                y_load<= '0';
                x_sub <= '0';
                y_sub <= '0';
                o_enb <= '0';
                x_reset <= '1';
                y_reset <= '1';
                o_reset <= '1';
            when 2 =>
                o_reset <= '0';
                x_reset <= '0';
                y_reset <= '0';
                x_load <= '1';
                y_load <= '1';
                x_sub <= '0' after 5 ns;
                y_sub <= '0' after 5 ns;
            when 8 =>
                x_load <= '0' after 1 ns;
                y_load <= '0' after 1 ns;
            when 3 =>
                y_sub <= '0';
                x_sub <= '1';
            when 4 =>
                x_sub <= '0';
                y_sub <= '1';
            when 5 =>
                o_enb <= '1';
            when 6 =>
                x_sel <= '1';
            when 7 =>
                y_sel <= '1';        
        end case ;
    end process;

    sequential : process(clk,reset)
    begin
        if reset='1' then
            state <= 1;
        elsif clk'event and clk='1' then
            case(state) is
                when 1 =>
                    state <= 2;
                when 2 =>
                    state <= 8;
                when 8 =>
                    if x_gt_y = '1' then
                        state <= 3;
                    elsif x_lt_y = '1' then
                        state <= 4;
                    elsif x_eq_y = '1' then
                        state <= 5;
                    end if;
                when 3 =>
                        state <= 6;
                when 4 =>
                        state <= 7;
                when 5 =>
                        null;
                when 6 =>
                        state <= 2;
                when 7 =>
                        state <= 2;
            end case ;
        end if;
    end process;
    
end arch;

Practice_GDC_CALCULATOR/GDC.vhdl
library ieee;
use ieee.std_logic_1164.all;

entity GDC is
    port(
        clk,reset : in std_logic;
        x,y : in std_logic_vector(3 downto 0);
        dataO : out std_logic_vector(3 downto 0)
    );
end GDC;

architecture arch of GDC is
    component controller is
        port(
            clk,reset: in std_logic;
            x_gt_y,x_eq_y,x_lt_y : in std_logic;
            x_sel,y_sel : out std_logic;
            x_load,y_load : out std_logic;
            x_reset,y_reset : out std_logic;
            x_sub,y_sub : out std_logic;
            o_enb,o_reset : out std_logic
        );
    end component;
    component datapath is
        port(
            x,y : in std_logic_vector(3 downto 0);
            x_sel,y_sel : in std_logic;
            clk : in std_logic;
            x_load,y_load,x_reset,y_reset : in std_logic;
            x_sub,y_sub : in std_logic;
            o_enb,o_reset : in std_logic;
            x_gt_y, x_eq_y, x_lt_y : out std_logic;
            z : out std_logic_vector(3 downto 0)
        );
    end component;
    signal x_gt_y, x_eq_y, x_lt_y : std_logic;
    signal x_sel,y_sel : std_logic;
    signal x_load,y_load,x_reset,y_reset : std_logic;
    signal x_sub,y_sub : std_logic;
    signal o_enb,o_reset : std_logic;
begin
    C0 : controller port map(clk,reset,x_gt_y, x_eq_y, x_lt_y,x_sel,y_sel,x_load,y_load,x_reset,y_reset,x_sub,y_sub,o_enb,o_reset);
    D0 : datapath port map(x,y,x_sel,y_sel,clk,x_load,y_load,x_reset,y_reset,x_sub,y_sub,o_enb,o_reset,x_gt_y, x_eq_y, x_lt_y,dataO);
end arch;

Practice_GDC_CALCULATOR/GDC_tb.vhdl
library ieee;
use ieee.std_logic_1164.all;

entity GDC_tb is
end GDC_tb;

architecture arch of GDC_tb is
    component GDC is
        port(
            clk,reset : in std_logic;
            x,y : in std_logic_vector(3 downto 0);
            dataO : out std_logic_vector(3 downto 0)
        );
    end component;
    signal clk,reset : std_logic := '0';
    signal x,y,dataO : std_logic_vector(3 downto 0) := "0000";
begin
    G0: GDC port map(clk,reset,x,y,dataO);

    CLKP : process
    begin
        clk <= not clk;
        wait for 2.5 ns;
    end process;
        
    SETP : process
    begin
        x <= "1000";
        y <= "0010";
        reset <= '1';
        wait for 5 ns;
        reset <= '0';
        wait for 100 ns;
        x <= "1100";
        y <= "0100";
        reset <= '1';
        wait for 5 ns;
        reset <= '0';
        wait for 100 ns;
        x <= "1111";
        y <= "1101";
        reset <= '1';
        wait for 5 ns;
        reset <= '0';
        wait;
    end process;
        
end arch;

Practice_GDC_CALCULATOR/GDC_tb.vcd
$date
  Mon May 11 14:35:29 2020
$end
$version
  GHDL v0
$end
$timescale
  1 fs
$end
$scope module standard $end
$upscope $end
$scope module std_logic_1164 $end
$upscope $end
$scope module numeric_std $end
$upscope $end
$scope module gdc_tb $end
$var reg 1 ! clk $end
$var reg 1 " reset $end
$var reg 4 # x[3:0] $end
$var reg 4 $ y[3:0] $end
$var reg 4 % datao[3:0] $end
$scope module g0 $end
$var reg 1 & clk $end
$var reg 1 ' reset $end
$var reg 4 ( x[3:0] $end
$var reg 4 ) y[3:0] $end
$var reg 4 * datao[3:0] $end
$var reg 1 + x_gt_y $end
$var reg 1 , x_eq_y $end
$var reg 1 - x_lt_y $end
$var reg 1 . x_sel $end
$var reg 1 / y_sel $end
$var reg 1 0 x_load $end
$var reg 1 1 y_load $end
$var reg 1 2 x_reset $end
$var reg 1 3 y_reset $end
$var reg 1 4 x_sub $end
$var reg 1 5 y_sub $end
$var reg 1 6 o_enb $end
$var reg 1 7 o_reset $end
$scope module c0 $end
$var reg 1 8 clk $end
$var reg 1 9 reset $end
$var reg 1 : x_gt_y $end
$var reg 1 ; x_eq_y $end
$var reg 1 < x_lt_y $end
$var reg 1 = x_sel $end
$var reg 1 > y_sel $end
$var reg 1 ? x_reset $end
$var reg 1 @ y_reset $end
$var reg 1 A x_load $end
$var reg 1 B y_load $end
$var reg 1 C x_sub $end
$var reg 1 D y_sub $end
$var reg 1 E o_enb $end
$var reg 1 F o_reset $end
$var integer 32 G state $end
$upscope $end
$scope module d0 $end
$var reg 4 H x[3:0] $end
$var reg 4 I y[3:0] $end
$var reg 1 J x_sel $end
$var reg 1 K y_sel $end
$var reg 1 L clk $end
$var reg 1 M x_load $end
$var reg 1 N y_load $end
$var reg 1 O x_reset $end
$var reg 1 P y_reset $end
$var reg 1 Q x_sub $end
$var reg 1 R y_sub $end
$var reg 1 S o_enb $end
$var reg 1 T o_reset $end
$var reg 1 U x_gt_y $end
$var reg 1 V x_eq_y $end
$var reg 1 W x_lt_y $end
$var reg 4 X z[3:0] $end
$var reg 4 Y xnew[3:0] $end
$var reg 4 Z ynew[3:0] $end
$var reg 4 [ inrx[3:0] $end
$var reg 4 \ inry[3:0] $end
$var reg 4 ] outrx[3:0] $end
$var reg 4 ^ outry[3:0] $end
$scope module muxx $end
$var reg 4 _ x[3:0] $end
$var reg 4 ` y[3:0] $end
$var reg 1 a sel $end
$var reg 4 b res[3:0] $end
$upscope $end
$scope module muxy $end
$var reg 4 c x[3:0] $end
$var reg 4 d y[3:0] $end
$var reg 1 e sel $end
$var reg 4 f res[3:0] $end
$upscope $end
$scope module regx $end
$var reg 4 g d_in[3:0] $end
$var reg 1 h clk $end
$var reg 1 i ld $end
$var reg 1 j reset $end
$var reg 4 k d_out[3:0] $end
$scope module ff_d0 $end
$var reg 1 l clk $end
$var reg 1 m ld $end
$var reg 1 n d $end
$var reg 1 o reset $end
$var reg 1 p q $end
$upscope $end
$scope module ff_d1 $end
$var reg 1 q clk $end
$var reg 1 r ld $end
$var reg 1 s d $end
$var reg 1 t reset $end
$var reg 1 u q $end
$upscope $end
$scope module ff_d2 $end
$var reg 1 v clk $end
$var reg 1 w ld $end
$var reg 1 x d $end
$var reg 1 y reset $end
$var reg 1 z q $end
$upscope $end
$scope module ff_d3 $end
$var reg 1 { clk $end
$var reg 1 | ld $end
$var reg 1 } d $end
$var reg 1 !" reset $end
$var reg 1 "" q $end
$upscope $end
$upscope $end
$scope module regy $end
$var reg 4 #" d_in[3:0] $end
$var reg 1 $" clk $end
$var reg 1 %" ld $end
$var reg 1 &" reset $end
$var reg 4 '" d_out[3:0] $end
$scope module ff_d0 $end
$var reg 1 (" clk $end
$var reg 1 )" ld $end
$var reg 1 *" d $end
$var reg 1 +" reset $end
$var reg 1 ," q $end
$upscope $end
$scope module ff_d1 $end
$var reg 1 -" clk $end
$var reg 1 ." ld $end
$var reg 1 /" d $end
$var reg 1 0" reset $end
$var reg 1 1" q $end
$upscope $end
$scope module ff_d2 $end
$var reg 1 2" clk $end
$var reg 1 3" ld $end
$var reg 1 4" d $end
$var reg 1 5" reset $end
$var reg 1 6" q $end
$upscope $end
$scope module ff_d3 $end
$var reg 1 7" clk $end
$var reg 1 8" ld $end
$var reg 1 9" d $end
$var reg 1 :" reset $end
$var reg 1 ;" q $end
$upscope $end
$upscope $end
$scope module cxy $end
$var reg 4 <" x[3:0] $end
$var reg 4 =" y[3:0] $end
$var reg 1 >" x_gt_y $end
$var reg 1 ?" x_eq_y $end
$var reg 1 @" x_lt_y $end
$upscope $end
$scope module subx $end
$var reg 1 A" en $end
$var reg 4 B" a[3:0] $end
$var reg 4 C" b[3:0] $end
$var reg 4 D" d[3:0] $end
$upscope $end
$scope module suby $end
$var reg 1 E" en $end
$var reg 4 F" a[3:0] $end
$var reg 4 G" b[3:0] $end
$var reg 4 H" d[3:0] $end
$upscope $end
$scope module outr $end
$var reg 4 I" d_in[3:0] $end
$var reg 1 J" clk $end
$var reg 1 K" ld $end
$var reg 1 L" reset $end
$var reg 4 M" d_out[3:0] $end
$scope module ff_d0 $end
$var reg 1 N" clk $end
$var reg 1 O" ld $end
$var reg 1 P" d $end
$var reg 1 Q" reset $end
$var reg 1 R" q $end
$upscope $end
$scope module ff_d1 $end
$var reg 1 S" clk $end
$var reg 1 T" ld $end
$var reg 1 U" d $end
$var reg 1 V" reset $end
$var reg 1 W" q $end
$upscope $end
$scope module ff_d2 $end
$var reg 1 X" clk $end
$var reg 1 Y" ld $end
$var reg 1 Z" d $end
$var reg 1 [" reset $end
$var reg 1 \" q $end
$upscope $end
$scope module ff_d3 $end
$var reg 1 ]" clk $end
$var reg 1 ^" ld $end
$var reg 1 _" d $end
$var reg 1 `" reset $end
$var reg 1 a" q $end
$upscope $end
$upscope $end
$upscope $end
$upscope $end
$upscope $end
$enddefinitions $end
#0
1!
1"
b1000 #
b0010 $
b0000 %
1&
1'
b1000 (
b0010 )
b0000 *
0+
1,
0-
0.
0/
00
01
12
13
04
05
06
17
18
19
0:
1;
0<
0=
0>
1?
1@
0A
0B
0C
0D
0E
1F
b1 G
b1000 H
b0010 I
0J
0K
1L
0M
0N
1O
1P
0Q
0R
0S
1T
0U
1V
0W
b0000 X
b0000 Y
b0000 Z
b1000 [
b0010 \
b0000 ]
b0000 ^
b1000 _
b0000 `
0a
b1000 b
b0010 c
b0000 d
0e
b0010 f
b1000 g
1h
0i
1j
b0000 k
1l
0m
0n
1o
0p
1q
0r
0s
1t
0u
1v
0w
0x
1y
0z
1{
0|
1}
1!"
0""
b0010 #"
1$"
0%"
1&"
b0000 '"
1("
0)"
0*"
1+"
0,"
1-"
0."
1/"
10"
01"
12"
03"
04"
15"
06"
17"
08"
09"
1:"
0;"
b0000 <"
b0000 ="
0>"
1?"
0@"
0A"
b0000 B"
b0000 C"
b0000 D"
0E"
b0000 F"
b0000 G"
b0000 H"
b0000 I"
1J"
0K"
1L"
b0000 M"
1N"
0O"
0P"
1Q"
0R"
1S"
0T"
0U"
1V"
0W"
1X"
0Y"
0Z"
1["
0\"
1]"
0^"
0_"
1`"
0a"
#2500000
0!
0&
08
0L
0h
0l
0q
0v
0{
0$"
0("
0-"
02"
07"
0J"
0N"
0S"
0X"
0]"
#5000000
1!
0"
1&
0'
10
11
02
03
07
18
09
0?
0@
1A
1B
0F
b10 G
1L
1M
1N
0O
0P
0T
1h
1i
0j
1l
1m
0o
1q
1r
0t
1v
1w
0y
1{
1|
0!"
1$"
1%"
0&"
1("
1)"
0+"
1-"
1."
00"
12"
13"
05"
17"
18"
0:"
1J"
0L"
1N"
0Q"
1S"
0V"
1X"
0["
1]"
0`"
#7500000
0!
0&
08
0L
0h
0l
0q
0v
0{
0$"
0("
0-"
02"
07"
0J"
0N"
0S"
0X"
0]"
#10000000
1!
1&
1+
0,
18
1:
0;
0C
0D
b1000 G
1L
1U
0V
b1000 Y
b0010 Z
b1000 ]
b0010 ^
b1000 `
b0010 d
1h
b1000 k
1l
1q
1v
1{
1""
1$"
b0010 '"
1("
1-"
11"
12"
17"
b1000 <"
b0010 ="
1>"
0?"
b1000 B"
b0010 C"
b1000 D"
b0010 F"
b1000 G"
b0010 H"
b1000 I"
1J"
1N"
1S"
1X"
1]"
1_"
#11000000
00
01
0A
0B
0M
0N
0i
0m
0r
0w
0|
0%"
0)"
0."
03"
08"
#12500000
0!
0&
08
0L
0h
0l
0q
0v
0{
0$"
0("
0-"
02"
07"
0J"
0N"
0S"
0X"
0]"
#15000000
1!
1&
14
18
1C
b11 G
1L
1Q
b0110 Y
b0110 `
1h
1l
1q
1v
1{
1$"
1("
1-"
12"
17"
1A"
b0110 D"
1J"
1N"
1S"
1X"
1]"
#17500000
0!
0&
08
0L
0h
0l
0q
0v
0{
0$"
0("
0-"
02"
07"
0J"
0N"
0S"
0X"
0]"
#20000000
1!
1&
1.
18
1=
b110 G
1J
1L
b0110 [
1a
b0110 b
b0110 g
1h
1l
1q
1s
1v
1x
1{
0}
1$"
1("
1-"
12"
17"
1J"
1N"
1S"
1X"
1]"
#22500000
0!
0&
08
0L
0h
0l
0q
0v
0{
0$"
0("
0-"
02"
07"
0J"
0N"
0S"
0X"
0]"
#25000000
1!
1&
10
11
18
1A
1B
b10 G
1L
1M
1N
1h
1i
1l
1m
1q
1r
1v
1w
1{
1|
1$"
1%"
1("
1)"
1-"
1."
12"
13"
17"
18"
1J"
1N"
1S"
1X"
1]"
#27500000
0!
0&
08
0L
0h
0l
0q
0v
0{
0$"
0("
0-"
02"
07"
0J"
0N"
0S"
0X"
0]"
#30000000
1!
1&
04
18
0C
0D
b1000 G
1L
0Q
b0110 Y
b0110 [
b0110 ]
b0110 `
b0110 b
b0110 g
1h
b0110 k
1l
1q
1s
1u
1v
1x
1z
1{
0}
0""
1$"
1("
1-"
12"
17"
b0110 <"
0A"
b0110 B"
b0110 D"
b0110 G"
b0110 I"
1J"
1N"
1S"
1U"
1X"
1Z"
1]"
0_"
#31000000
00
01
0A
0B
0M
0N
0i
0m
0r
0w
0|
0%"
0)"
0."
03"
08"
#32500000
0!
0&
08
0L
0h
0l
0q
0v
0{
0$"
0("
0-"
02"
07"
0J"
0N"
0S"
0X"
0]"
#35000000
1!
1&
14
18
1C
b11 G
1L
1Q
b0100 Y
b0100 [
b0100 `
b0100 b
b0100 g
1h
1l
1q
0s
1v
1{
1$"
1("
1-"
12"
17"
1A"
b0100 D"
1J"
1N"
1S"
1X"
1]"
#37500000
0!
0&
08
0L
0h
0l
0q
0v
0{
0$"
0("
0-"
02"
07"
0J"
0N"
0S"
0X"
0]"
#40000000
1!
1&
18
b110 G
1L
1h
1l
1q
1v
1{
1$"
1("
1-"
12"
17"
1J"
1N"
1S"
1X"
1]"
#42500000
0!
0&
08
0L
0h
0l
0q
0v
0{
0$"
0("
0-"
02"
07"
0J"
0N"
0S"
0X"
0]"
#45000000
1!
1&
10
11
18
1A
1B
b10 G
1L
1M
1N
1h
1i
1l
1m
1q
1r
1v
1w
1{
1|
1$"
1%"
1("
1)"
1-"
1."
12"
13"
17"
18"
1J"
1N"
1S"
1X"
1]"
#47500000
0!
0&
08
0L
0h
0l
0q
0v
0{
0$"
0("
0-"
02"
07"
0J"
0N"
0S"
0X"
0]"
#50000000
1!
1&
04
18
0C
0D
b1000 G
1L
0Q
b0100 Y
b0100 [
b0100 ]
b0100 `
b0100 b
b0100 g
1h
b0100 k
1l
1q
0s
0u
1v
1{
1$"
1("
1-"
12"
17"
b0100 <"
0A"
b0100 B"
b0100 D"
b0100 G"
b0100 I"
1J"
1N"
1S"
0U"
1X"
1]"
#51000000
00
01
0A
0B
0M
0N
0i
0m
0r
0w
0|
0%"
0)"
0."
03"
08"
#52500000
0!
0&
08
0L
0h
0l
0q
0v
0{
0$"
0("
0-"
02"
07"
0J"
0N"
0S"
0X"
0]"
#55000000
1!
1&
14
18
1C
b11 G
1L
1Q
b0010 Y
b0010 [
b0010 `
b0010 b
b0010 g
1h
1l
1q
1s
1v
0x
1{
1$"
1("
1-"
12"
17"
1A"
b0010 D"
1J"
1N"
1S"
1X"
1]"
#57500000
0!
0&
08
0L
0h
0l
0q
0v
0{
0$"
0("
0-"
02"
07"
0J"
0N"
0S"
0X"
0]"
#60000000
1!
1&
18
b110 G
1L
1h
1l
1q
1v
1{
1$"
1("
1-"
12"
17"
1J"
1N"
1S"
1X"
1]"
#62500000
0!
0&
08
0L
0h
0l
0q
0v
0{
0$"
0("
0-"
02"
07"
0J"
0N"
0S"
0X"
0]"
#65000000
1!
1&
10
11
18
1A
1B
b10 G
1L
1M
1N
1h
1i
1l
1m
1q
1r
1v
1w
1{
1|
1$"
1%"
1("
1)"
1-"
1."
12"
13"
17"
18"
1J"
1N"
1S"
1X"
1]"
#67500000
0!
0&
08
0L
0h
0l
0q
0v
0{
0$"
0("
0-"
02"
07"
0J"
0N"
0S"
0X"
0]"
#70000000
1!
1&
0+
1,
04
18
0:
1;
0C
0D
b1000 G
1L
0Q
0U
1V
b0010 Y
b0010 [
b0010 ]
b0010 `
b0010 b
b0010 g
1h
b0010 k
1l
1q
1s
1u
1v
0x
0z
1{
1$"
1("
1-"
12"
17"
b0010 <"
0>"
1?"
0A"
b0010 B"
b0010 D"
b0010 G"
b0010 I"
1J"
1N"
1S"
1U"
1X"
0Z"
1]"
#71000000
00
01
0A
0B
0M
0N
0i
0m
0r
0w
0|
0%"
0)"
0."
03"
08"
#72500000
0!
0&
08
0L
0h
0l
0q
0v
0{
0$"
0("
0-"
02"
07"
0J"
0N"
0S"
0X"
0]"
#75000000
1!
1&
16
18
1E
b101 G
1L
1S
1h
1l
1q
1v
1{
1$"
1("
1-"
12"
17"
1J"
1K"
1N"
1O"
1S"
1T"
1X"
1Y"
1]"
1^"
#77500000
0!
0&
08
0L
0h
0l
0q
0v
0{
0$"
0("
0-"
02"
07"
0J"
0N"
0S"
0X"
0]"
#80000000
1!
b0010 %
1&
b0010 *
18
1L
b0010 X
1h
1l
1q
1v
1{
1$"
1("
1-"
12"
17"
1J"
b0010 M"
1N"
1S"
1W"
1X"
1]"
#82500000
0!
0&
08
0L
0h
0l
0q
0v
0{
0$"
0("
0-"
02"
07"
0J"
0N"
0S"
0X"
0]"
#85000000
1!
1&
18
1L
1h
1l
1q
1v
1{
1$"
1("
1-"
12"
17"
1J"
1N"
1S"
1X"
1]"
#87500000
0!
0&
08
0L
0h
0l
0q
0v
0{
0$"
0("
0-"
02"
07"
0J"
0N"
0S"
0X"
0]"
#90000000
1!
1&
18
1L
1h
1l
1q
1v
1{
1$"
1("
1-"
12"
17"
1J"
1N"
1S"
1X"
1]"
#92500000
0!
0&
08
0L
0h
0l
0q
0v
0{
0$"
0("
0-"
02"
07"
0J"
0N"
0S"
0X"
0]"
#95000000
1!
1&
18
1L
1h
1l
1q
1v
1{
1$"
1("
1-"
12"
17"
1J"
1N"
1S"
1X"
1]"
#97500000
0!
0&
08
0L
0h
0l
0q
0v
0{
0$"
0("
0-"
02"
07"
0J"
0N"
0S"
0X"
0]"
#100000000
1!
1&
18
1L
1h
1l
1q
1v
1{
1$"
1("
1-"
12"
17"
1J"
1N"
1S"
1X"
1]"
#102500000
0!
0&
08
0L
0h
0l
0q
0v
0{
0$"
0("
0-"
02"
07"
0J"
0N"
0S"
0X"
0]"
#105000000
1!
1"
b1100 #
b0100 $
b0000 %
1&
1'
b1100 (
b0100 )
b0000 *
0.
12
13
06
17
18
19
0=
1?
1@
0E
1F
b1 G
b1100 H
b0100 I
0J
1L
1O
1P
0S
1T
b0000 X
b0000 Y
b0000 Z
b1100 [
b0100 \
b0000 ]
b0000 ^
b1100 _
b0000 `
0a
b1100 b
b0100 c
b0000 d
b0100 f
b1100 g
1h
1j
b0000 k
1l
1o
1q
0s
1t
0u
1v
1x
1y
1{
1}
1!"
b0100 #"
1$"
1&"
b0000 '"
1("
1+"
1-"
0/"
10"
01"
12"
14"
15"
17"
1:"
b0000 <"
b0000 ="
b0000 B"
b0000 C"
b0000 D"
b0000 F"
b0000 G"
b0000 H"
b0000 I"
1J"
0K"
1L"
b0000 M"
1N"
0O"
1Q"
1S"
0T"
0U"
1V"
0W"
1X"
0Y"
1["
1]"
0^"
1`"
#107500000
0!
0&
08
0L
0h
0l
0q
0v
0{
0$"
0("
0-"
02"
07"
0J"
0N"
0S"
0X"
0]"
#110000000
1!
0"
1&
0'
10
11
02
03
07
18
09
0?
0@
1A
1B
0F
b10 G
1L
1M
1N
0O
0P
0T
1h
1i
0j
1l
1m
0o
1q
1r
0t
1v
1w
0y
1{
1|
0!"
1$"
1%"
0&"
1("
1)"
0+"
1-"
1."
00"
12"
13"
05"
17"
18"
0:"
1J"
0L"
1N"
0Q"
1S"
0V"
1X"
0["
1]"
0`"
#112500000
0!
0&
08
0L
0h
0l
0q
0v
0{
0$"
0("
0-"
02"
07"
0J"
0N"
0S"
0X"
0]"
#115000000
1!
1&
1+
0,
18
1:
0;
0C
0D
b1000 G
1L
1U
0V
b1100 Y
b0100 Z
b1100 ]
b0100 ^
b1100 `
b0100 d
1h
b1100 k
1l
1q
1v
1z
1{
1""
1$"
b0100 '"
1("
1-"
12"
16"
17"
b1100 <"
b0100 ="
1>"
0?"
b1100 B"
b0100 C"
b1100 D"
b0100 F"
b1100 G"
b0100 H"
b1100 I"
1J"
1N"
1S"
1X"
1Z"
1]"
1_"
#116000000
00
01
0A
0B
0M
0N
0i
0m
0r
0w
0|
0%"
0)"
0."
03"
08"
#117500000
0!
0&
08
0L
0h
0l
0q
0v
0{
0$"
0("
0-"
02"
07"
0J"
0N"
0S"
0X"
0]"
#120000000
1!
1&
14
18
1C
b11 G
1L
1Q
b1000 Y
b1000 `
1h
1l
1q
1v
1{
1$"
1("
1-"
12"
17"
1A"
b1000 D"
1J"
1N"
1S"
1X"
1]"
#122500000
0!
0&
08
0L
0h
0l
0q
0v
0{
0$"
0("
0-"
02"
07"
0J"
0N"
0S"
0X"
0]"
#125000000
1!
1&
1.
18
1=
b110 G
1J
1L
b1000 [
1a
b1000 b
b1000 g
1h
1l
1q
1v
0x
1{
1$"
1("
1-"
12"
17"
1J"
1N"
1S"
1X"
1]"
#127500000
0!
0&
08
0L
0h
0l
0q
0v
0{
0$"
0("
0-"
02"
07"
0J"
0N"
0S"
0X"
0]"
#130000000
1!
1&
10
11
18
1A
1B
b10 G
1L
1M
1N
1h
1i
1l
1m
1q
1r
1v
1w
1{
1|
1$"
1%"
1("
1)"
1-"
1."
12"
13"
17"
18"
1J"
1N"
1S"
1X"
1]"
#132500000
0!
0&
08
0L
0h
0l
0q
0v
0{
0$"
0("
0-"
02"
07"
0J"
0N"
0S"
0X"
0]"
#135000000
1!
1&
04
18
0C
0D
b1000 G
1L
0Q
b1000 Y
b1000 [
b1000 ]
b1000 `
b1000 b
b1000 g
1h
b1000 k
1l
1q
1v
0x
0z
1{
1$"
1("
1-"
12"
17"
b1000 <"
0A"
b1000 B"
b1000 D"
b1000 G"
b1000 I"
1J"
1N"
1S"
1X"
0Z"
1]"
#136000000
00
01
0A
0B
0M
0N
0i
0m
0r
0w
0|
0%"
0)"
0."
03"
08"
#137500000
0!
0&
08
0L
0h
0l
0q
0v
0{
0$"
0("
0-"
02"
07"
0J"
0N"
0S"
0X"
0]"
#140000000
1!
1&
14
18
1C
b11 G
1L
1Q
b0100 Y
b0100 [
b0100 `
b0100 b
b0100 g
1h
1l
1q
1v
1x
1{
0}
1$"
1("
1-"
12"
17"
1A"
b0100 D"
1J"
1N"
1S"
1X"
1]"
#142500000
0!
0&
08
0L
0h
0l
0q
0v
0{
0$"
0("
0-"
02"
07"
0J"
0N"
0S"
0X"
0]"
#145000000
1!
1&
18
b110 G
1L
1h
1l
1q
1v
1{
1$"
1("
1-"
12"
17"
1J"
1N"
1S"
1X"
1]"
#147500000
0!
0&
08
0L
0h
0l
0q
0v
0{
0$"
0("
0-"
02"
07"
0J"
0N"
0S"
0X"
0]"
#150000000
1!
1&
10
11
18
1A
1B
b10 G
1L
1M
1N
1h
1i
1l
1m
1q
1r
1v
1w
1{
1|
1$"
1%"
1("
1)"
1-"
1."
12"
13"
17"
18"
1J"
1N"
1S"
1X"
1]"
#152500000
0!
0&
08
0L
0h
0l
0q
0v
0{
0$"
0("
0-"
02"
07"
0J"
0N"
0S"
0X"
0]"
#155000000
1!
1&
0+
1,
04
18
0:
1;
0C
0D
b1000 G
1L
0Q
0U
1V
b0100 Y
b0100 [
b0100 ]
b0100 `
b0100 b
b0100 g
1h
b0100 k
1l
1q
1v
1x
1z
1{
0}
0""
1$"
1("
1-"
12"
17"
b0100 <"
0>"
1?"
0A"
b0100 B"
b0100 D"
b0100 G"
b0100 I"
1J"
1N"
1S"
1X"
1Z"
1]"
0_"
#156000000
00
01
0A
0B
0M
0N
0i
0m
0r
0w
0|
0%"
0)"
0."
03"
08"
#157500000
0!
0&
08
0L
0h
0l
0q
0v
0{
0$"
0("
0-"
02"
07"
0J"
0N"
0S"
0X"
0]"
#160000000
1!
1&
16
18
1E
b101 G
1L
1S
1h
1l
1q
1v
1{
1$"
1("
1-"
12"
17"
1J"
1K"
1N"
1O"
1S"
1T"
1X"
1Y"
1]"
1^"
#162500000
0!
0&
08
0L
0h
0l
0q
0v
0{
0$"
0("
0-"
02"
07"
0J"
0N"
0S"
0X"
0]"
