8bitsShifterRegister/e_74194.vhdl
library IEEE;
use IEEE.numeric_bit.all;

entity e_74194 is
    port(
        clk,clr,s0,s1,sdr,sdl : in bit;
        D : in bit_vector(3 downto 0);
        Z : out bit_vector(3 downto 0)
    );
end e_74194;

architecture arch of e_74194 is
    signal s1s0 : bit_vector(1 downto 0);
    signal intZ : bit_vector(3 downto 0);
begin
    s1s0 <= s1 & s0;
    Z <= intZ;
    process(clk,clr)
        begin
            if clr = '0' then 
                intZ <= "0000";
            elsif clk'event and clk='1' then
                case s1s0 is 
                    when "11" => intZ <= D;
                    when "10" => intZ <= sdr & intZ(3 downto 1);
                    when "01" => intZ <= intZ(2 downto 0) & sdl;
                    when "00" => null;
                end case;
            end if;
    end process;
end arch;

8bitsShifterRegister/e_8bitShiftRegister.vhdl
library IEEE;
use IEEE.numeric_bit.all;

entity e_8bitShiftRegister is
    port(
        clk,clr,s0,s1,sdr,sdl : in bit;
        D : in bit_vector(7 downto 0);
        Z : out bit_vector(7 downto 0)
    );
end e_8bitShiftRegister;

architecture arch of e_8bitShiftRegister is
    component e_74194 is
        port(
            clk,clr,s0,s1,sdr,sdl : in bit;
            D : in bit_vector(3 downto 0);
            Z : out bit_vector(3 downto 0)
        );
    end component;
    signal Z1,Z0: bit_vector(3 downto 0);
begin
    E0 : e_74194 port map(clk,clr,s0,s1,Z1(0),sdl,D(3 downto 0),Z0);
    E1 : e_74194 port map(clk,clr,s0,s1,sdr,Z0(3),D(7 downto 4),Z1);
    Z<= Z1 & Z0;
end arch;

8bitsShifterRegister/e_8bitShiftRegister_tb.vhdl
library IEEE;
use IEEE.numeric_bit.all;

entity e_8bitShiftRegister_tb is
end e_8bitShiftRegister_tb;

architecture arch of e_8bitShiftRegister_tb is
    component e_8bitShiftRegister is
        port(
            clk,clr,s0,s1,sdr,sdl : in bit;
            D : in bit_vector(7 downto 0);
            Z : out bit_vector(7 downto 0)
        );
    end component;
    signal clk,clr,s0,s1,sdr,sdl : bit := '0';
    signal D : bit_vector(7 downto 0);
    signal Z : bit_vector(7 downto 0);
begin
    E0 : e_8bitShiftRegister port map(clk,clr,s0,s1,sdr,sdl,D,Z);    

    CLK_process : process
    begin
        CLK<='0';
        wait for 5 ns;
        CLK<='1';
        wait for 5 ns;
    end process;
    
    SET_process : process
    begin
        clr <= '1';
        s0 <= '1';
        sdl <= '1';
        wait for 30 ns;
        sdl <= '0';
        wait for 30 ns;
        s0 <= '0';
        s1 <= '1';
        sdr <= '1';
        wait for 30 ns;
        sdr <= '0';
        wait for 30 ns;
        s0 <= '1';
        D <= "01010101";
        wait for 10 ns;
        s0 <= '0';
        s0 <= '1';
        wait for 20 ns;
        clr <= '0';
        wait;
    end process;
    
end arch;

8bitsShifterRegister/e_8bitShiftRegister_tb.vcd
$date
  Sat May  9 01:56:25 2020
$end
$version
  GHDL v0
$end
$timescale
  1 fs
$end
$scope module standard $end
$upscope $end
$scope module numeric_bit $end
$upscope $end
$scope module e_8bitshiftregister_tb $end
$var reg 1 ! clk $end
$var reg 1 " clr $end
$var reg 1 # s0 $end
$var reg 1 $ s1 $end
$var reg 1 % sdr $end
$var reg 1 & sdl $end
$var reg 8 ' d[7:0] $end
$var reg 8 ( z[7:0] $end
$scope module e0 $end
$var reg 1 ) clk $end
$var reg 1 * clr $end
$var reg 1 + s0 $end
$var reg 1 , s1 $end
$var reg 1 - sdr $end
$var reg 1 . sdl $end
$var reg 8 / d[7:0] $end
$var reg 8 0 z[7:0] $end
$var reg 4 1 z1[3:0] $end
$var reg 4 2 z0[3:0] $end
$scope module e0 $end
$var reg 1 3 clk $end
$var reg 1 4 clr $end
$var reg 1 5 s0 $end
$var reg 1 6 s1 $end
$var reg 1 7 sdr $end
$var reg 1 8 sdl $end
$var reg 4 9 d[3:0] $end
$var reg 4 : z[3:0] $end
$var reg 2 ; s1s0[1:0] $end
$var reg 4 < intz[3:0] $end
$upscope $end
$scope module e1 $end
$var reg 1 = clk $end
$var reg 1 > clr $end
$var reg 1 ? s0 $end
$var reg 1 @ s1 $end
$var reg 1 A sdr $end
$var reg 1 B sdl $end
$var reg 4 C d[3:0] $end
$var reg 4 D z[3:0] $end
$var reg 2 E s1s0[1:0] $end
$var reg 4 F intz[3:0] $end
$upscope $end
$upscope $end
$upscope $end
$enddefinitions $end
#0
0!
1"
1#
0$
0%
1&
b00000000 '
b00000000 (
0)
1*
1+
0,
0-
1.
b00000000 /
b00000000 0
b0000 1
b0000 2
03
14
15
06
07
18
b0000 9
b0000 :
b01 ;
b0000 <
0=
1>
1?
0@
0A
0B
b0000 C
b0000 D
b01 E
b0000 F
#5000000
1!
b00000001 (
1)
b00000001 0
b0001 2
13
b0001 :
b0001 <
1=
#10000000
0!
0)
03
0=
#15000000
1!
b00000011 (
1)
b00000011 0
b0011 2
13
b0011 :
b0011 <
1=
#20000000
0!
0)
03
0=
#25000000
1!
b00000111 (
1)
b00000111 0
b0111 2
13
b0111 :
b0111 <
1=
#30000000
0!
0&
0)
0.
03
08
0=
#35000000
1!
b00001110 (
1)
b00001110 0
b1110 2
13
b1110 :
b1110 <
1=
1B
#40000000
0!
0)
03
0=
#45000000
1!
b00011100 (
1)
b00011100 0
b0001 1
b1100 2
13
17
b1100 :
b1100 <
1=
b0001 D
b0001 F
#50000000
0!
0)
03
0=
#55000000
1!
b00111000 (
1)
b00111000 0
b0011 1
b1000 2
13
b1000 :
b1000 <
1=
b0011 D
b0011 F
#60000000
0!
0#
1$
1%
0)
0+
1,
1-
03
05
16
b10 ;
0=
0?
1@
1A
b10 E
#65000000
1!
b10011100 (
1)
b10011100 0
b1001 1
b1100 2
13
b1100 :
b1100 <
1=
b1001 D
b1001 F
#70000000
0!
0)
03
0=
#75000000
1!
b11001110 (
1)
b11001110 0
b1100 1
b1110 2
13
07
b1110 :
b1110 <
1=
b1100 D
b1100 F
#80000000
0!
0)
03
0=
#85000000
1!
b11100111 (
1)
b11100111 0
b1110 1
b0111 2
13
b0111 :
b0111 <
1=
0B
b1110 D
b1110 F
#90000000
0!
0%
0)
0-
03
0=
0A
#95000000
1!
b01110011 (
1)
b01110011 0
b0111 1
b0011 2
13
17
b0011 :
b0011 <
1=
b0111 D
b0111 F
#100000000
0!
0)
03
0=
#105000000
1!
b00111001 (
1)
b00111001 0
b0011 1
b1001 2
13
b1001 :
b1001 <
1=
1B
b0011 D
b0011 F
#110000000
0!
0)
03
0=
#115000000
1!
b00011100 (
1)
b00011100 0
b0001 1
b1100 2
13
b1100 :
b1100 <
1=
b0001 D
b0001 F
#120000000
0!
1#
b01010101 '
0)
1+
b01010101 /
03
15
b0101 9
b11 ;
0=
1?
b0101 C
b11 E
#125000000
1!
b01010101 (
1)
b01010101 0
b0101 1
b0101 2
13
b0101 :
b0101 <
1=
0B
b0101 D
b0101 F
#130000000
0!
0)
03
0=
#135000000
1!
1)
13
1=
#140000000
0!
0)
03
0=
#145000000
1!
1)
13
1=
#150000000
0!
0"
b00000000 (
0)
0*
b00000000 0
b0000 1
b0000 2
03
04
07
b0000 :
b0000 <
0=
0>
b0000 D
b0000 F
