Synchronys Counter/e_74F169.vhdl
library IEEE;
use IEEE.numeric_bit.all;

entity e_74F169 is
    port(    
        CP,CEP,CET,UD,PE : in bit;
        D : in bit_vector(3 downto 0);
        TC: out bit;
        Q : out bit_vector(3 downto 0)
    );
end e_74F169;

architecture arch of e_74F169 is
    signal intQ : unsigned(3 downto 0) := "0000"; 
begin
    TC <= '1' when (TO_INTEGER(intQ)=0 and UD='0') or (TO_INTEGER(intQ)=15 and UD='1') else '0';
    Q <= bit_vector(intQ);
    process(CP)
    begin
        if cp'event and cp='1' then
            if pe = '0' then
                intQ <= unsigned(D);
            elsif CEP = '0' and CET = '0' then
                if ud = '1' then
                    intQ <= intQ + 1;
                else 
                    intQ <= intQ - 1;
                end if;
            end if;
        end if;
    end process;
end arch;

Synchronys Counter/e2_74F169.vhdl
library IEEE;
use IEEE.numeric_bit.all;

entity e2_74F169 is
    port(    
        CP,CEP,CET,UD : in bit;
        TC: out bit;
        Q : out bit_vector(7 downto 0)
    );
end e2_74F169;

architecture arch of e2_74F169 is
    component e_74F169 is
        port(    
            CP,CEP,CET,UD,PE : in bit;
            D : in bit_vector(3 downto 0);
            TC: out bit;
            Q : out bit_vector(3 downto 0)
        );
    end component;
    signal TC_1,TC_2,TC1,TC2,nTC1,nTC2,intPE1,intPE2 : bit;
    signal intD : bit_vector(3 downto 0);
    signal intQ : bit_vector(7 downto 0);
begin
    
    TC1 <= '1' when (TO_INTEGER(unsigned(intQ(3 downto 0))) = 9 and UD = '1') or (TO_INTEGER(unsigned(intQ(3 downto 0))) = 0 and UD = '0') else '0';
    TC2 <= '1' when (TO_INTEGER(unsigned(intQ(7 downto 4))) = 9 and UD = '1') or (TO_INTEGER(unsigned(intQ(7 downto 4))) = 0 and UD = '0') else '0';
    nTC1 <= not TC1;
    nTC2 <= not TC2; 

    intPE1 <= '0' when TC1='1' else '1';
    intPE2 <= '0' when TC2='1' and TC1='1' else '1';

    intD <= "1001" when UD = '0' else "0000";
    
    E1: e_74F169 port map(cp, cep, cet,ud,intPE1,intD,TC_1,intQ(3 downto 0));
    E2: e_74F169 port map(cp,nTC1,nTC1,ud,intPE2,intD,TC_2,intQ(7 downto 4));
    
    Q <= intQ;
end arch;

Synchronys Counter/e2_74F169_tb.vhdl
library IEEE;
use IEEE.numeric_bit.all;

entity e2_74F169_tb is
end e2_74F169_tb;

architecture arch of e2_74F169_tb is
    component e2_74F169 is
        port(    
            CP,CEP,CET,UD : in bit;
            TC: out bit;
            Q : out bit_vector(7 downto 0)
        );
    end component;
    signal CP,CEP,CET,UD : bit := '0';
    signal D : bit_vector(7 downto 0);
    signal TC: bit;
    signal Q : bit_vector(7 downto 0);
begin
    E0: e2_74F169 port map(CP,CEP,CET,UD,TC,Q);
    CP_process : process
    begin
        CP<='0';
        wait for 5 ns;
        CP<='1';
        wait for 5 ns;
    end process;

    PE_process : process
    begin
        wait for 200 ns;
        UD<='1';
        wait;
    end process;
end arch;

Synchronys Counter/e2_74F169_tb.vcd
$date
  Sat May  9 01:02:22 2020
$end
$version
  GHDL v0
$end
$timescale
  1 fs
$end
$scope module standard $end
$upscope $end
$scope module numeric_bit $end
$upscope $end
$scope module e2_74f169_tb $end
$var reg 1 ! cp $end
$var reg 1 " cep $end
$var reg 1 # cet $end
$var reg 1 $ ud $end
$var reg 8 % d[7:0] $end
$var reg 1 & tc $end
$var reg 8 ' q[7:0] $end
$scope module e0 $end
$var reg 1 ( cp $end
$var reg 1 ) cep $end
$var reg 1 * cet $end
$var reg 1 + ud $end
$var reg 1 , tc $end
$var reg 8 - q[7:0] $end
$var reg 1 . tc_1 $end
$var reg 1 / tc_2 $end
$var reg 1 0 tc1 $end
$var reg 1 1 tc2 $end
$var reg 1 2 ntc1 $end
$var reg 1 3 ntc2 $end
$var reg 1 4 intpe1 $end
$var reg 1 5 intpe2 $end
$var reg 4 6 intd[3:0] $end
$var reg 8 7 intq[7:0] $end
$scope module e1 $end
$var reg 1 8 cp $end
$var reg 1 9 cep $end
$var reg 1 : cet $end
$var reg 1 ; ud $end
$var reg 1 < pe $end
$var reg 4 = d[3:0] $end
$var reg 1 > tc $end
$var reg 4 ? q[3:0] $end
$var reg 4 @ intq[3:0] $end
$upscope $end
$scope module e2 $end
$var reg 1 A cp $end
$var reg 1 B cep $end
$var reg 1 C cet $end
$var reg 1 D ud $end
$var reg 1 E pe $end
$var reg 4 F d[3:0] $end
$var reg 1 G tc $end
$var reg 4 H q[3:0] $end
$var reg 4 I intq[3:0] $end
$upscope $end
$upscope $end
$upscope $end
$enddefinitions $end
#0
0!
0"
0#
0$
b00000000 %
0&
b00000000 '
0(
0)
0*
0+
0,
b00000000 -
1.
1/
10
11
02
03
04
05
b1001 6
b00000000 7
08
09
0:
0;
0<
b1001 =
1>
b0000 ?
b0000 @
0A
0B
0C
0D
0E
b1001 F
1G
b0000 H
b0000 I
#5000000
1!
b10011001 '
1(
b10011001 -
0.
0/
00
01
12
13
14
15
b10011001 7
18
1<
0>
b1001 ?
b1001 @
1A
1B
1C
1E
0G
b1001 H
b1001 I
#10000000
0!
0(
08
0A
#15000000
1!
b10011000 '
1(
b10011000 -
b10011000 7
18
b1000 ?
b1000 @
1A
#20000000
0!
0(
08
0A
#25000000
1!
b10010111 '
1(
b10010111 -
b10010111 7
18
b0111 ?
b0111 @
1A
#30000000
0!
0(
08
0A
#35000000
1!
b10010110 '
1(
b10010110 -
b10010110 7
18
b0110 ?
b0110 @
1A
#40000000
0!
0(
08
0A
#45000000
1!
b10010101 '
1(
b10010101 -
b10010101 7
18
b0101 ?
b0101 @
1A
#50000000
0!
0(
08
0A
#55000000
1!
b10010100 '
1(
b10010100 -
b10010100 7
18
b0100 ?
b0100 @
1A
#60000000
0!
0(
08
0A
#65000000
1!
b10010011 '
1(
b10010011 -
b10010011 7
18
b0011 ?
b0011 @
1A
#70000000
0!
0(
08
0A
#75000000
1!
b10010010 '
1(
b10010010 -
b10010010 7
18
b0010 ?
b0010 @
1A
#80000000
0!
0(
08
0A
#85000000
1!
b10010001 '
1(
b10010001 -
b10010001 7
18
b0001 ?
b0001 @
1A
#90000000
0!
0(
08
0A
#95000000
1!
b10010000 '
1(
b10010000 -
1.
10
02
04
b10010000 7
18
0<
1>
b0000 ?
b0000 @
1A
0B
0C
#100000000
0!
0(
08
0A
#105000000
1!
b10001001 '
1(
b10001001 -
0.
00
12
14
b10001001 7
18
1<
0>
b1001 ?
b1001 @
1A
1B
1C
b1000 H
b1000 I
#110000000
0!
0(
08
0A
#115000000
1!
b10001000 '
1(
b10001000 -
b10001000 7
18
b1000 ?
b1000 @
1A
#120000000
0!
0(
08
0A
#125000000
1!
b10000111 '
1(
b10000111 -
b10000111 7
18
b0111 ?
b0111 @
1A
#130000000
0!
0(
08
0A
#135000000
1!
b10000110 '
1(
b10000110 -
b10000110 7
18
b0110 ?
b0110 @
1A
#140000000
0!
0(
08
0A
#145000000
1!
b10000101 '
1(
b10000101 -
b10000101 7
18
b0101 ?
b0101 @
1A
#150000000
0!
0(
08
0A
#155000000
1!
b10000100 '
1(
b10000100 -
b10000100 7
18
b0100 ?
b0100 @
1A
#160000000
0!
0(
08
0A
#165000000
1!
b10000011 '
1(
b10000011 -
b10000011 7
18
b0011 ?
b0011 @
1A
#170000000
0!
0(
08
0A
#175000000
1!
b10000010 '
1(
b10000010 -
b10000010 7
18
b0010 ?
b0010 @
1A
#180000000
0!
0(
08
0A
#185000000
1!
b10000001 '
1(
b10000001 -
b10000001 7
18
b0001 ?
b0001 @
1A
#190000000
0!
0(
08
0A
#195000000
1!
b10000000 '
1(
b10000000 -
1.
10
02
04
b10000000 7
18
0<
1>
b0000 ?
b0000 @
1A
0B
0C
#200000000
0!
1$
0(
1+
0.
00
12
14
b0000 6
08
1;
1<
b0000 =
0>
0A
1B
1C
1D
b0000 F
#205000000
1!
b10000001 '
1(
b10000001 -
b10000001 7
18
b0001 ?
b0001 @
1A
#210000000
0!
0(
08
0A
#215000000
1!
b10000010 '
1(
b10000010 -
b10000010 7
18
b0010 ?
b0010 @
1A
#220000000
0!
0(
08
0A
#225000000
1!
b10000011 '
1(
b10000011 -
b10000011 7
18
b0011 ?
b0011 @
1A
#230000000
0!
0(
08
0A
#235000000
1!
b10000100 '
1(
b10000100 -
b10000100 7
18
b0100 ?
b0100 @
1A
#240000000
0!
0(
08
0A
#245000000
1!
b10000101 '
1(
b10000101 -
b10000101 7
18
b0101 ?
b0101 @
1A
#250000000
0!
0(
08
0A
#255000000
1!
b10000110 '
1(
b10000110 -
b10000110 7
18
b0110 ?
b0110 @
1A
#260000000
0!
0(
08
0A
#265000000
1!
b10000111 '
1(
b10000111 -
b10000111 7
18
b0111 ?
b0111 @
1A
#270000000
0!
0(
08
0A
#275000000
1!
b10001000 '
1(
b10001000 -
b10001000 7
18
b1000 ?
b1000 @
1A
#280000000
0!
0(
08
0A
#285000000
1!
b10001001 '
1(
b10001001 -
10
02
04
b10001001 7
18
0<
b1001 ?
b1001 @
1A
0B
0C
#290000000
0!
0(
08
0A
#295000000
1!
b10010000 '
1(
b10010000 -
00
11
12
03
14
b10010000 7
18
1<
b0000 ?
b0000 @
1A
1B
1C
b1001 H
b1001 I
#300000000
0!
0(
08
0A
#305000000
1!
b10010001 '
1(
b10010001 -
b10010001 7
18
b0001 ?
b0001 @
1A
#310000000
0!
0(
08
0A
#315000000
1!
b10010010 '
1(
b10010010 -
b10010010 7
18
b0010 ?
b0010 @
1A
#320000000
0!
0(
08
0A
#325000000
1!
b10010011 '
1(
b10010011 -
b10010011 7
18
b0011 ?
b0011 @
1A
#330000000
0!
0(
08
0A
#335000000
1!
b10010100 '
1(
b10010100 -
b10010100 7
18
b0100 ?
b0100 @
1A
#340000000
0!
0(
08
0A
#345000000
1!
b10010101 '
1(
b10010101 -
b10010101 7
18
b0101 ?
b0101 @
1A
#350000000
0!
0(
08
0A
#355000000
1!
b10010110 '
1(
b10010110 -
b10010110 7
18
b0110 ?
b0110 @
1A
#360000000
0!
0(
08
0A
#365000000
1!
b10010111 '
1(
b10010111 -
b10010111 7
18
b0111 ?
b0111 @
1A
#370000000
0!
0(
08
0A
#375000000
1!
b10011000 '
1(
b10011000 -
b10011000 7
18
b1000 ?
b1000 @
1A
#380000000
0!
0(
08
0A
#385000000
1!
b10011001 '
1(
b10011001 -
10
02
04
05
b10011001 7
18
0<
b1001 ?
b1001 @
1A
0B
0C
0E
#390000000
0!
0(
08
0A
#395000000
1!
b00000000 '
1(
b00000000 -
00
01
12
13
14
15
b00000000 7
18
1<
b0000 ?
b0000 @
1A
1B
1C
1E
b0000 H
b0000 I
#400000000
0!
0(
08
0A
#405000000
1!
b00000001 '
1(
b00000001 -
b00000001 7
18
b0001 ?
b0001 @
1A
#410000000
0!
0(
08
0A
#415000000
1!
b00000010 '
1(
b00000010 -
b00000010 7
18
b0010 ?
b0010 @
1A
#420000000
0!
0(
08
0A
