Synchronys Counter/e_74F169.vhdl
library IEEE;
use IEEE.numeric_bit.all;

entity e_74F169 is
    port(    
        CP,CEP,CET,UD,PE : in bit;
        D : in bit_vector(3 downto 0);
        TC: out bit;
        Q : out bit_vector(3 downto 0)
    );
end e_74F169;

architecture arch of e_74F169 is
    signal intQ : unsigned(3 downto 0) := "0000"; 
begin
    TC <= '1' when (TO_INTEGER(intQ)=0 and UD='0') or (TO_INTEGER(intQ)=15 and UD='1') else '0';
    Q <= bit_vector(intQ);
    process(CP)
    begin
        if cp'event and cp='1' then
            if pe = '0' then
                intQ <= unsigned(D);
            elsif CEP = '0' and CET = '0' then
                if ud = '1' then
                    intQ <= intQ + 1;
                else 
                    intQ <= intQ - 1;
                end if;
            end if;
        end if;
    end process;
end arch;

Synchronys Counter/e_74F169_tb.vhdl
library IEEE;
use IEEE.numeric_bit.all;

entity e_74F169_tb is
end e_74F169_tb;

architecture arch of e_74F169_tb is
    component e_74F169 is
        port(    
            CP,CEP,CET,UD,PE : in bit;
            D : in bit_vector(3 downto 0);
            TC: out bit;
            Q : out bit_vector(3 downto 0)
        );
    end component;
    signal CP,CEP,CET,UD,PE : bit := '0';
    signal D : bit_vector(3 downto 0);
    signal TC: bit;
    signal Q : bit_vector(3 downto 0);
begin
    E0: e_74F169 port map(CP,CEP,CET,UD,PE,D,TC,Q);
    CP_process : process
    begin
        CP<='0';
        wait for 5 ns;
        CP<='1';
        wait for 5 ns;
    end process;

    PE_process : process
    begin
        PE<='1';
        wait for 115 ns;
        UD<='1';
        wait for 115 ns;
        D <= "1111";
        PE<='0';
        wait for 6 ns;
        PE <= '1';
        wait;
    end process;
end arch;

Synchronys Counter/e_74F169_tb.vcd
$date
  Sat May  9 01:11:38 2020
$end
$version
  GHDL v0
$end
$timescale
  1 fs
$end
$scope module standard $end
$upscope $end
$scope module numeric_bit $end
$upscope $end
$scope module e_74f169_tb $end
$var reg 1 ! cp $end
$var reg 1 " cep $end
$var reg 1 # cet $end
$var reg 1 $ ud $end
$var reg 1 % pe $end
$var reg 4 & d[3:0] $end
$var reg 1 ' tc $end
$var reg 4 ( q[3:0] $end
$scope module e0 $end
$var reg 1 ) cp $end
$var reg 1 * cep $end
$var reg 1 + cet $end
$var reg 1 , ud $end
$var reg 1 - pe $end
$var reg 4 . d[3:0] $end
$var reg 1 / tc $end
$var reg 4 0 q[3:0] $end
$var reg 4 1 intq[3:0] $end
$upscope $end
$upscope $end
$enddefinitions $end
#0
0!
0"
0#
0$
1%
b0000 &
1'
b0000 (
0)
0*
0+
0,
1-
b0000 .
1/
b0000 0
b0000 1
#5000000
1!
0'
b1111 (
1)
0/
b1111 0
b1111 1
#10000000
0!
0)
#15000000
1!
b1110 (
1)
b1110 0
b1110 1
#20000000
0!
0)
#25000000
1!
b1101 (
1)
b1101 0
b1101 1
#30000000
0!
0)
#35000000
1!
b1100 (
1)
b1100 0
b1100 1
#40000000
0!
0)
#45000000
1!
b1011 (
1)
b1011 0
b1011 1
#50000000
0!
0)
#55000000
1!
b1010 (
1)
b1010 0
b1010 1
#60000000
0!
0)
#65000000
1!
b1001 (
1)
b1001 0
b1001 1
#70000000
0!
0)
#75000000
1!
b1000 (
1)
b1000 0
b1000 1
#80000000
0!
0)
#85000000
1!
b0111 (
1)
b0111 0
b0111 1
#90000000
0!
0)
#95000000
1!
b0110 (
1)
b0110 0
b0110 1
#100000000
0!
0)
#105000000
1!
b0101 (
1)
b0101 0
b0101 1
#110000000
0!
0)
#115000000
1!
1$
b0110 (
1)
1,
b0110 0
b0110 1
#120000000
0!
0)
#125000000
1!
b0111 (
1)
b0111 0
b0111 1
#130000000
0!
0)
#135000000
1!
b1000 (
1)
b1000 0
b1000 1
#140000000
0!
0)
#145000000
1!
b1001 (
1)
b1001 0
b1001 1
#150000000
0!
0)
#155000000
1!
b1010 (
1)
b1010 0
b1010 1
#160000000
0!
0)
#165000000
1!
b1011 (
1)
b1011 0
b1011 1
#170000000
0!
0)
#175000000
1!
b1100 (
1)
b1100 0
b1100 1
#180000000
0!
0)
#185000000
1!
b1101 (
1)
b1101 0
b1101 1
#190000000
0!
0)
#195000000
1!
b1110 (
1)
b1110 0
b1110 1
#200000000
0!
0)
#205000000
1!
1'
b1111 (
1)
1/
b1111 0
b1111 1
#210000000
0!
0)
#215000000
1!
0'
b0000 (
1)
0/
b0000 0
b0000 1
#220000000
0!
0)
#225000000
1!
b0001 (
1)
b0001 0
b0001 1
#230000000
0!
0%
b1111 &
0)
0-
b1111 .
#235000000
1!
1'
b1111 (
1)
1/
b1111 0
b1111 1
#236000000
1%
1-
#240000000
0!
0)
#245000000
1!
0'
b0000 (
1)
0/
b0000 0
b0000 1
#250000000
0!
0)
#255000000
1!
b0001 (
1)
b0001 0
b0001 1
#260000000
0!
0)
#265000000
1!
b0010 (
1)
b0010 0
b0010 1
#270000000
0!
0)
#275000000
1!
b0011 (
1)
b0011 0
b0011 1
#280000000
0!
0)
#285000000
1!
b0100 (
1)
b0100 0
b0100 1
#290000000
0!
0)
#295000000
1!
b0101 (
1)
b0101 0
b0101 1
#300000000
0!
0)
#305000000
1!
b0110 (
1)
b0110 0
b0110 1
#310000000
0!
0)
#315000000
1!
b0111 (
1)
b0111 0
b0111 1
#320000000
0!
0)
#325000000
1!
b1000 (
1)
b1000 0
b1000 1
#330000000
0!
0)
#335000000
1!
b1001 (
1)
b1001 0
b1001 1
#340000000
0!
0)
#345000000
1!
b1010 (
1)
b1010 0
b1010 1
#350000000
0!
0)
#355000000
1!
b1011 (
1)
b1011 0
b1011 1
#360000000
0!
0)
#365000000
1!
b1100 (
1)
b1100 0
b1100 1
#370000000
0!
0)
#375000000
1!
b1101 (
1)
b1101 0
b1101 1
#380000000
0!
0)
#385000000
1!
b1110 (
1)
b1110 0
b1110 1
#390000000
0!
0)
#395000000
1!
1'
b1111 (
1)
1/
b1111 0
b1111 1
#400000000
0!
0)
#405000000
1!
0'
b0000 (
1)
0/
b0000 0
b0000 1
#410000000
0!
0)
#415000000
1!
b0001 (
1)
b0001 0
b0001 1
#420000000
0!
0)
