Practice5/FF_JK.vhdl
entity FF_JK is
    port(
        CLK,J,K,PRESET,CLEAR,EN: in bit;
        Q,Qn: out bit
        );
end entity;
 
architecture arch of FF_JK is
    signal intQ: bit;
begin
    Q<=intQ;
    Qn<=not intQ;
    process(CLK,PRESET,CLEAR)
        begin

        if CLEAR='0' then
            intQ<='0';
        elsif PRESET='0' then
            intQ<='1';
        elsif EN='0' then
            null;
        elsif CLK'event and CLK='1' then
            if J = '0' and K = '0' then
                intQ <= intQ;
            elsif J = '0' and K = '1' then
                intQ <= '0';
            elsif J = '1' and K = '0' then
                intQ <= '1';
            else
                intQ <= not intQ;
            end if;
        end if;
    end process;
end arch;

Practice5/Counter4B.vhdl
entity Counter4B is
    port(
        CLK: in bit;
        CLEAR: in bit;
        PRESET: in bit_vector(3 downto 0);
        EN: in bit;
        Z: out bit_vector(3 downto 0)
        );
end Counter4B;
 
architecture arch of Counter4B is
    component FF_JK is
        port(
            CLK,J,K,PRESET,CLEAR,EN: in bit;
            Q,Qn: out bit
            );
    end component;
    signal intQ: bit_vector(3 downto 0);
    signal intJK: bit_vector(3 downto 0);
    signal intQN: bit_vector(3 downto 0);
begin
    intJK(0)<='1';
    intJK(1)<=intQ(0);
    intJK(2)<=intQ(0) and intQ(1);
    intJK(3)<=intJK(2) and intQ(2);
    F0: FF_JK port map(CLK=>CLK,J=>intJK(0),K=>intJK(0),PRESET=>PRESET(0),CLEAR=>CLEAR,Q=>intQ(0),Qn=>intQN(0),EN=>EN);
    F1: FF_JK port map(CLK=>CLK,J=>intJK(1),K=>intJK(1),PRESET=>PRESET(1),CLEAR=>CLEAR,Q=>intQ(1),Qn=>intQN(1),EN=>EN);
    F2: FF_JK port map(CLK=>CLK,J=>intJK(2),K=>intJK(2),PRESET=>PRESET(2),CLEAR=>CLEAR,Q=>intQ(2),Qn=>intQN(2),EN=>EN);
    F3: FF_JK port map(CLK=>CLK,J=>intJK(3),K=>intJK(3),PRESET=>PRESET(3),CLEAR=>CLEAR,Q=>intQ(3),Qn=>intQN(3),EN=>EN);
    Z<=intQ;
    
end arch;

Practice5/Counter0_5.vhdl
entity Counter0_5 is
    port(
        CLK: in bit;
        CLEAR: in bit;
        PRESET: in bit_vector(3 downto 0);
        EN: in bit;
        Z: out bit_vector(3 downto 0)
        );
end Counter0_5;
 
architecture arch of Counter0_5 is
    component Counter4B is
        port(
            CLK: in bit;
            CLEAR: in bit;
            PRESET: in bit_vector(3 downto 0);
            EN: in bit;
            Z: out bit_vector(3 downto 0)
            );
    end component;
    signal intQ4: bit_vector(3 downto 0);
    signal clear0_5 : bit;
begin
    Z<=intQ4;
    clear0_5 <= CLEAR and not (intQ4(1) and intQ4(2));
    B4: Counter4B port map(CLK,clear0_5,PRESET,EN,intQ4);
end arch;

Practice5/Counter0_5_tb.vhdl
entity Counter0_5_tb is
end Counter0_5_tb;
 
architecture arch of Counter0_5_tb is
    component Counter0_5 is
        port(
            CLK: in bit;
            CLEAR: in bit;
            PRESET: in bit_vector(3 downto 0);
            EN: in bit;
            Z: out bit_vector(3 downto 0)
            );
    end component;
    signal CLK: bit := '0';
    signal CLEAR: bit := '1';
    signal PRESET: bit_vector(3 downto 0) := "1111";
    signal EN: bit := '1';
    signal Z: bit_vector(3 downto 0);
begin
    FS0: Counter0_5 port map(CLK,CLEAR,PRESET,EN,Z);
    CLK_process : process
    begin
        CLK<='0';
        wait for 5 ns;
        CLK<='1';
        wait for 5 ns;
    end process;

    Set_process : process
    begin
        CLEAR<='0';
        wait for 5 ns;
        CLEAR<='1';
        wait;
    end process;
end arch;

Practice5/Counter0_5_tb.vcd
$date
  Fri May  8 22:23:36 2020
$end
$version
  GHDL v0
$end
$timescale
  1 fs
$end
$scope module standard $end
$upscope $end
$scope module counter0_5_tb $end
$var reg 1 ! clk $end
$var reg 1 " clear $end
$var reg 4 # preset[3:0] $end
$var reg 1 $ en $end
$var reg 4 % z[3:0] $end
$scope module fs0 $end
$var reg 1 & clk $end
$var reg 1 ' clear $end
$var reg 4 ( preset[3:0] $end
$var reg 1 ) en $end
$var reg 4 * z[3:0] $end
$var reg 4 + intq4[3:0] $end
$var reg 1 , clear0_5 $end
$scope module b4 $end
$var reg 1 - clk $end
$var reg 1 . clear $end
$var reg 4 / preset[3:0] $end
$var reg 1 0 en $end
$var reg 4 1 z[3:0] $end
$var reg 4 2 intq[3:0] $end
$var reg 4 3 intjk[3:0] $end
$var reg 4 4 intqn[3:0] $end
$scope module f0 $end
$var reg 1 5 clk $end
$var reg 1 6 j $end
$var reg 1 7 k $end
$var reg 1 8 preset $end
$var reg 1 9 clear $end
$var reg 1 : en $end
$var reg 1 ; q $end
$var reg 1 < qn $end
$var reg 1 = intq $end
$upscope $end
$scope module f1 $end
$var reg 1 > clk $end
$var reg 1 ? j $end
$var reg 1 @ k $end
$var reg 1 A preset $end
$var reg 1 B clear $end
$var reg 1 C en $end
$var reg 1 D q $end
$var reg 1 E qn $end
$var reg 1 F intq $end
$upscope $end
$scope module f2 $end
$var reg 1 G clk $end
$var reg 1 H j $end
$var reg 1 I k $end
$var reg 1 J preset $end
$var reg 1 K clear $end
$var reg 1 L en $end
$var reg 1 M q $end
$var reg 1 N qn $end
$var reg 1 O intq $end
$upscope $end
$scope module f3 $end
$var reg 1 P clk $end
$var reg 1 Q j $end
$var reg 1 R k $end
$var reg 1 S preset $end
$var reg 1 T clear $end
$var reg 1 U en $end
$var reg 1 V q $end
$var reg 1 W qn $end
$var reg 1 X intq $end
$upscope $end
$upscope $end
$upscope $end
$upscope $end
$enddefinitions $end
#0
0!
0"
b1111 #
1$
b0000 %
0&
0'
b1111 (
1)
b0000 *
b0000 +
0,
0-
0.
b1111 /
10
b0000 1
b0000 2
b0001 3
b1111 4
05
16
17
18
09
1:
0;
1<
0=
0>
0?
0@
1A
0B
1C
0D
1E
0F
0G
0H
0I
1J
0K
1L
0M
1N
0O
0P
0Q
0R
1S
0T
1U
0V
1W
0X
#5000000
1!
1"
1&
1'
1,
1-
1.
15
19
1>
1B
1G
1K
1P
1T
#10000000
0!
0&
0-
05
0>
0G
0P
#15000000
1!
b0001 %
1&
b0001 *
b0001 +
1-
b0001 1
b0001 2
b0011 3
b1110 4
15
1;
0<
1=
1>
1?
1@
1G
1P
#20000000
0!
0&
0-
05
0>
0G
0P
#25000000
1!
b0010 %
1&
b0010 *
b0010 +
1-
b0010 1
b0010 2
b0001 3
b1101 4
15
0;
1<
0=
1>
0?
0@
1D
0E
1F
1G
1P
#30000000
0!
0&
0-
05
0>
0G
0P
#35000000
1!
b0011 %
1&
b0011 *
b0011 +
1-
b0011 1
b0011 2
b0111 3
b1100 4
15
1;
0<
1=
1>
1?
1@
1G
1H
1I
1P
#40000000
0!
0&
0-
05
0>
0G
0P
#45000000
1!
b0100 %
1&
b0100 *
b0100 +
1-
b0100 1
b0100 2
b0001 3
b1011 4
15
0;
1<
0=
1>
0?
0@
0D
1E
0F
1G
0H
0I
1M
0N
1O
1P
0Q
0R
#50000000
0!
0&
0-
05
0>
0G
0P
#55000000
1!
b0101 %
1&
b0101 *
b0101 +
1-
b0101 1
b0101 2
b0011 3
b1010 4
15
1;
0<
1=
1>
1?
1@
1G
1P
#60000000
0!
0&
0-
05
0>
0G
0P
#65000000
1!
b0000 %
1&
b0000 *
b0000 +
1,
1-
1.
b0000 1
b0000 2
b0001 3
b1111 4
15
19
0;
1<
0=
1>
0?
0@
1B
0D
1E
0F
1G
1K
0M
1N
0O
1P
1T
#70000000
0!
0&
0-
05
0>
0G
0P
#75000000
1!
b0001 %
1&
b0001 *
b0001 +
1-
b0001 1
b0001 2
b0011 3
b1110 4
15
1;
0<
1=
1>
1?
1@
1G
1P
#80000000
0!
0&
0-
05
0>
0G
0P
#85000000
1!
b0010 %
1&
b0010 *
b0010 +
1-
b0010 1
b0010 2
b0001 3
b1101 4
15
0;
1<
0=
1>
0?
0@
1D
0E
1F
1G
1P
#90000000
0!
0&
0-
05
0>
0G
0P
#95000000
1!
b0011 %
1&
b0011 *
b0011 +
1-
b0011 1
b0011 2
b0111 3
b1100 4
15
1;
0<
1=
1>
1?
1@
1G
1H
1I
1P
#100000000
0!
0&
0-
05
0>
0G
0P
#105000000
1!
b0100 %
1&
b0100 *
b0100 +
1-
b0100 1
b0100 2
b0001 3
b1011 4
15
0;
1<
0=
1>
0?
0@
0D
1E
0F
1G
0H
0I
1M
0N
1O
1P
0Q
0R
#110000000
0!
0&
0-
05
0>
0G
0P
#115000000
1!
b0101 %
1&
b0101 *
b0101 +
1-
b0101 1
b0101 2
b0011 3
b1010 4
15
1;
0<
1=
1>
1?
1@
1G
1P
#120000000
0!
0&
0-
05
0>
0G
0P
#125000000
1!
b0000 %
1&
b0000 *
b0000 +
1,
1-
1.
b0000 1
b0000 2
b0001 3
b1111 4
15
19
0;
1<
0=
1>
0?
0@
1B
0D
1E
0F
1G
1K
0M
1N
0O
1P
1T
#130000000
0!
0&
0-
05
0>
0G
0P
#135000000
1!
b0001 %
1&
b0001 *
b0001 +
1-
b0001 1
b0001 2
b0011 3
b1110 4
15
1;
0<
1=
1>
1?
1@
1G
1P
#140000000
0!
0&
0-
05
0>
0G
0P
#145000000
1!
b0010 %
1&
b0010 *
b0010 +
1-
b0010 1
b0010 2
b0001 3
b1101 4
15
0;
1<
0=
1>
0?
0@
1D
0E
1F
1G
1P
#150000000
0!
0&
0-
05
0>
0G
0P
#155000000
1!
b0011 %
1&
b0011 *
b0011 +
1-
b0011 1
b0011 2
b0111 3
b1100 4
15
1;
0<
1=
1>
1?
1@
1G
1H
1I
1P
#160000000
0!
0&
0-
05
0>
0G
0P
#165000000
1!
b0100 %
1&
b0100 *
b0100 +
1-
b0100 1
b0100 2
b0001 3
b1011 4
15
0;
1<
0=
1>
0?
0@
0D
1E
0F
1G
0H
0I
1M
0N
1O
1P
0Q
0R
#170000000
0!
0&
0-
05
0>
0G
0P
#175000000
1!
b0101 %
1&
b0101 *
b0101 +
1-
b0101 1
b0101 2
b0011 3
b1010 4
15
1;
0<
1=
1>
1?
1@
1G
1P
#180000000
0!
0&
0-
05
0>
0G
0P
#185000000
1!
b0000 %
1&
b0000 *
b0000 +
1,
1-
1.
b0000 1
b0000 2
b0001 3
b1111 4
15
19
0;
1<
0=
1>
0?
0@
1B
0D
1E
0F
1G
1K
0M
1N
0O
1P
1T
#190000000
0!
0&
0-
05
0>
0G
0P
#195000000
1!
b0001 %
1&
b0001 *
b0001 +
1-
b0001 1
b0001 2
b0011 3
b1110 4
15
1;
0<
1=
1>
1?
1@
1G
1P
#200000000
0!
0&
0-
05
0>
0G
0P
#205000000
1!
b0010 %
1&
b0010 *
b0010 +
1-
b0010 1
b0010 2
b0001 3
b1101 4
15
0;
1<
0=
1>
0?
0@
1D
0E
1F
1G
1P
#210000000
0!
0&
0-
05
0>
0G
0P
#215000000
1!
b0011 %
1&
b0011 *
b0011 +
1-
b0011 1
b0011 2
b0111 3
b1100 4
15
1;
0<
1=
1>
1?
1@
1G
1H
1I
1P
#220000000
0!
0&
0-
05
0>
0G
0P
#225000000
1!
b0100 %
1&
b0100 *
b0100 +
1-
b0100 1
b0100 2
b0001 3
b1011 4
15
0;
1<
0=
1>
0?
0@
0D
1E
0F
1G
0H
0I
1M
0N
1O
1P
0Q
0R
#230000000
0!
0&
0-
05
0>
0G
0P
#235000000
1!
b0101 %
1&
b0101 *
b0101 +
1-
b0101 1
b0101 2
b0011 3
b1010 4
15
1;
0<
1=
1>
1?
1@
1G
1P
#240000000
0!
0&
0-
05
0>
0G
0P
#245000000
1!
b0000 %
1&
b0000 *
b0000 +
1,
1-
1.
b0000 1
b0000 2
b0001 3
b1111 4
15
19
0;
1<
0=
1>
0?
0@
1B
0D
1E
0F
1G
1K
0M
1N
0O
1P
1T
#250000000
0!
0&
0-
05
0>
0G
0P
#255000000
1!
b0001 %
1&
b0001 *
b0001 +
1-
b0001 1
b0001 2
b0011 3
b1110 4
15
1;
0<
1=
1>
1?
1@
1G
1P
#260000000
0!
0&
0-
05
0>
0G
0P
#265000000
1!
b0010 %
1&
b0010 *
b0010 +
1-
b0010 1
b0010 2
b0001 3
b1101 4
15
0;
1<
0=
1>
0?
0@
1D
0E
1F
1G
1P
#270000000
0!
0&
0-
05
0>
0G
0P
#275000000
1!
b0011 %
1&
b0011 *
b0011 +
1-
b0011 1
b0011 2
b0111 3
b1100 4
15
1;
0<
1=
1>
1?
1@
1G
1H
1I
1P
#280000000
0!
0&
0-
05
0>
0G
0P
#285000000
1!
b0100 %
1&
b0100 *
b0100 +
1-
b0100 1
b0100 2
b0001 3
b1011 4
15
0;
1<
0=
1>
0?
0@
0D
1E
0F
1G
0H
0I
1M
0N
1O
1P
0Q
0R
#290000000
0!
0&
0-
05
0>
0G
0P
#295000000
1!
b0101 %
1&
b0101 *
b0101 +
1-
b0101 1
b0101 2
b0011 3
b1010 4
15
1;
0<
1=
1>
1?
1@
1G
1P
#300000000
0!
0&
0-
05
0>
0G
0P
#305000000
1!
b0000 %
1&
b0000 *
b0000 +
1,
1-
1.
b0000 1
b0000 2
b0001 3
b1111 4
15
19
0;
1<
0=
1>
0?
0@
1B
0D
1E
0F
1G
1K
0M
1N
0O
1P
1T
#310000000
0!
0&
0-
05
0>
0G
0P
#315000000
1!
b0001 %
1&
b0001 *
b0001 +
1-
b0001 1
b0001 2
b0011 3
b1110 4
15
1;
0<
1=
1>
1?
1@
1G
1P
#320000000
0!
0&
0-
05
0>
0G
0P
#325000000
1!
b0010 %
1&
b0010 *
b0010 +
1-
b0010 1
b0010 2
b0001 3
b1101 4
15
0;
1<
0=
1>
0?
0@
1D
0E
1F
1G
1P
#330000000
0!
0&
0-
05
0>
0G
0P
#335000000
1!
b0011 %
1&
b0011 *
b0011 +
1-
b0011 1
b0011 2
b0111 3
b1100 4
15
1;
0<
1=
1>
1?
1@
1G
1H
1I
1P
#340000000
0!
0&
0-
05
0>
0G
0P
#345000000
1!
b0100 %
1&
b0100 *
b0100 +
1-
b0100 1
b0100 2
b0001 3
b1011 4
15
0;
1<
0=
1>
0?
0@
0D
1E
0F
1G
0H
0I
1M
0N
1O
1P
0Q
0R
#350000000
0!
0&
0-
05
0>
0G
0P
#355000000
1!
b0101 %
1&
b0101 *
b0101 +
1-
b0101 1
b0101 2
b0011 3
b1010 4
15
1;
0<
1=
1>
1?
1@
1G
1P
#360000000
0!
0&
0-
05
0>
0G
0P
#365000000
1!
b0000 %
1&
b0000 *
b0000 +
1,
1-
1.
b0000 1
b0000 2
b0001 3
b1111 4
15
19
0;
1<
0=
1>
0?
0@
1B
0D
1E
0F
1G
1K
0M
1N
0O
1P
1T
#370000000
0!
0&
0-
05
0>
0G
0P
#375000000
1!
b0001 %
1&
b0001 *
b0001 +
1-
b0001 1
b0001 2
b0011 3
b1110 4
15
1;
0<
1=
1>
1?
1@
1G
1P
#380000000
0!
0&
0-
05
0>
0G
0P
#385000000
1!
b0010 %
1&
b0010 *
b0010 +
1-
b0010 1
b0010 2
b0001 3
b1101 4
15
0;
1<
0=
1>
0?
0@
1D
0E
1F
1G
1P
#390000000
0!
0&
0-
05
0>
0G
0P
#395000000
1!
b0011 %
1&
b0011 *
b0011 +
1-
b0011 1
b0011 2
b0111 3
b1100 4
15
1;
0<
1=
1>
1?
1@
1G
1H
1I
1P
#400000000
0!
0&
0-
05
0>
0G
0P
#405000000
1!
b0100 %
1&
b0100 *
b0100 +
1-
b0100 1
b0100 2
b0001 3
b1011 4
15
0;
1<
0=
1>
0?
0@
0D
1E
0F
1G
0H
0I
1M
0N
1O
1P
0Q
0R
#410000000
0!
0&
0-
05
0>
0G
0P
#415000000
1!
b0101 %
1&
b0101 *
b0101 +
1-
b0101 1
b0101 2
b0011 3
b1010 4
15
1;
0<
1=
1>
1?
1@
1G
1P
