interfaces/keyboard_v1.vhdl
 
library ieee;
use ieee.std_logic_1164.all;
use ieee.numeric_std.all;


entity keyboard_v1 is 
    port(
        kbd_clk, kbd_data, clk : in std_logic;
        reset, enable : in std_logic;
        scan_code : out std_logic_vector(7 downto 0);
        scan_ready : out std_logic;
        scan_error : out std_logic
    );
end entity;

architecture arch of keyboard_v1 is

    signal filter : std_logic_vector(7 downto 0) := "00000000";
    signal kbd_clk_filtered : std_logic := '0';
    signal read_char : std_logic := '0';
    signal ready_set : std_logic := '0';
    signal parity_pred : std_logic := '0';
    signal incount : unsigned(3 downto 0) := "0000";
    signal shiftin : std_logic_vector(8 downto 0) := "000000000";

begin
   
    clk_filter : process
    begin
        wait until clk'event and clk = '1';
        filter(6 downto 0) <= filter(7 downto 1);
        filter(7) <= kbd_clk;
        if filter = x"FF" then 
            kbd_clk_filtered <= '1';
        elsif filter = x"00" then
            kbd_clk_filtered <= '0';
        end if;
    end process;
   
    -- Lectura de la información serial del dispositivo
    process
    begin
        wait until (kbd_clk_filtered'event and kbd_clk_filtered = '0');
        if reset = '1' then
            incount <= "0000";
            read_char <= '0';
            parity_pred <= '1';
        else
            if kbd_data = '0' and read_char = '0' then
                read_char <= '1';
                ready_set <= '0';
                parity_pred <= '1';
            else
                if read_char = '1' then
                    if incount < "1001" then
                        if kbd_data = '1' and incount < "1000" then
                            parity_pred <= not parity_pred;
                        end if;
                        
                        incount <= incount + 1;
                        shiftin(7 downto 0) <= shiftin(8 downto 1);
                        shiftin(8) <= kbd_data;
                        ready_set <= '0';
                    
                    else
                        if shiftin(8) = parity_pred then
                            scan_error <= '0';
                        else
                            scan_error <= '1';
                        end if;
                        scan_code <= shiftin(7 downto 0);
                        read_char <= '0';
                        ready_set <= '1';
                        incount <= "0000";
                    end if;
                end if;
            end if;
        end if;
    end process;

    process (enable, ready_set)
    begin
        if enable = '1' then
            scan_ready <= '0';
        elsif ready_set'event then
            scan_ready <= ready_set;
        end if;
    end process;
end arch;

interfaces/keyboard_v1_tb.vhdl
library ieee;
use ieee.std_logic_1164.all;
use ieee.numeric_std.all;
use ieee.std_logic_textio.all;

library std;
use std.textio.all;


entity keyboard_v1_tb is
    constant period : time := 40 ns ; -- Señal de reloj de 25MHz
    constant bit_period : time := 60 us ; -- Keyboard clock ~ 16.7 Khz max
end entity;

architecture arch of keyboard_v1_tb is
    component keyboard_v1 is 
        port(
            kbd_clk, kbd_data, clk : in std_logic;
            reset, enable : in std_logic;
            scan_code : out std_logic_vector(7 downto 0);
            scan_ready : out std_logic;
            scan_error : out std_logic
        );
    end component;

    signal clk : std_logic := '0';
    signal reset : std_logic;
    signal kbd_clk : std_logic := '1';
    signal kbd_data : std_logic := 'H';
    signal enable : std_logic := '0';
    signal scan_ready : std_logic := '0';
    signal scan_error : std_logic;
    signal scan_code : std_logic_vector(7 downto 0);

    type dataRecord is record
        code : std_logic_vector(7 downto 0);
        parity : std_logic;
    end record;
 
    type dataArray is array (natural range <>) of dataRecord;
    constant data : dataArray := (
                                    (code => x"3B", parity => '0'),
                                    (code => x"44", parity => '1'),
                                    (code => x"21", parity => '0'), 
                                    (code => x"24", parity => '1')
                                );

    begin 

    UUT : keyboard_v1 port map (kbd_clk, kbd_data, clk, reset, enable, scan_code, scan_ready, scan_error );

    -- Señal de reloj del sistema
    clk <= not clk after (period / 2);
    reset <= '1', '0' after period;

    process
        procedure send_code( sc : dataRecord ) is
        begin
            kbd_clk <= 'H';
            kbd_data <= 'H';
            
            wait for (bit_period/2);
            kbd_data <= '0'; -- Start bit
            
            wait for (bit_period/2);
            kbd_clk <= '0';
            wait for (bit_period/2);
            kbd_clk <= '1';

            for i in 0 to 7 loop
                kbd_data <= sc.code(i);
                
                wait for (bit_period/2);
                kbd_clk <= '0';
                wait for (bit_period/2);
                kbd_clk <= '1';

            end loop;

            -- bit de paridad
            kbd_data <= sc.parity;
            
            wait for (bit_period/2);
            kbd_clk <= '0';
            wait for (bit_period/2);
            kbd_clk <= '1';
            
            -- stop bit
            kbd_data <= '1';
            
            wait for (bit_period/2);
            kbd_clk <= '0';
            wait for (bit_period/2);
            kbd_clk <= '1';
            
            kbd_data <= 'H';
            
            wait for (bit_period * 3);
        end procedure send_code;
    
       begin
        wait for bit_period;
        for i in data'range loop
            send_code(data(i));
        end loop;
        wait;
    end process;

    process
        variable l : line;
    begin
        wait until scan_ready'event and scan_ready = '1';
        
        if scan_error = '1' then
            write (l, string'("Scan error : "));
        else
            write (l, string'("Scan code  : "));
        end if;

        write (l, scan_code);
        writeline(output, l);
        
    end process;

end arch;

interfaces/keyboard_v1_tb.vcd
$date
  Wed Jun 10 15:48:55 2020
$end
$version
  GHDL v0
$end
$timescale
  1 fs
$end
$scope module standard $end
$upscope $end
$scope module std_logic_1164 $end
$upscope $end
$scope module numeric_std $end
$upscope $end
$scope module textio $end
$upscope $end
$scope module std_logic_textio $end
$upscope $end
$scope module keyboard_v1_tb $end
$var reg 1 ! clk $end
$var reg 1 " reset $end
$var reg 1 # kbd_clk $end
$var reg 1 $ kbd_data $end
$var reg 1 % enable $end
$var reg 1 & scan_ready $end
$var reg 1 ' scan_error $end
$var reg 8 ( scan_code[7:0] $end
$scope module uut $end
$var reg 1 ) kbd_clk $end
$var reg 1 * kbd_data $end
$var reg 1 + clk $end
$var reg 1 , reset $end
$var reg 1 - enable $end
$var reg 8 . scan_code[7:0] $end
$var reg 1 / scan_ready $end
$var reg 1 0 scan_error $end
$var reg 8 1 filter[7:0] $end
$var reg 1 2 kbd_clk_filtered $end
$var reg 1 3 read_char $end
$var reg 1 4 ready_set $end
$var reg 1 5 parity_pred $end
$var reg 4 6 incount[3:0] $end
$var reg 9 7 shiftin[8:0] $end
$upscope $end
$upscope $end
$enddefinitions $end
#0
0!
1"
1#
H$
0%
U&
U'
bUUUUUUUU (
1)
H*
0+
1,
0-
bUUUUUUUU .
U/
U0
b00000000 1
02
03
04
05
b0000 6
b000000000 7
#20000000
1!
1+
b10000000 1
#40000000
0!
0"
0+
0,
#60000000
1!
1+
b11000000 1
#80000000
0!
0+
#100000000
1!
1+
b11100000 1
#120000000
0!
0+
#140000000
1!
1+
b11110000 1
#160000000
0!
0+
#180000000
1!
1+
b11111000 1
#200000000
0!
0+
#220000000
1!
1+
b11111100 1
#240000000
0!
0+
#260000000
1!
1+
b11111110 1
#280000000
0!
0+
#300000000
1!
1+
b11111111 1
