interfaces/keyboard_v2.vhdl
 
library ieee;
use ieee.std_logic_1164.all;
use ieee.numeric_std.all;


entity keyboard_v2 is 
    port(
        kbd_clk, kbd_data, clk : in std_logic;
        reset, enable : in std_logic;
        scan_code : out std_logic_vector(7 downto 0);
        scan_parity : out std_logic;
        scan_ready : out std_logic;
        scan_error : out std_logic
    );
end entity;

architecture arch of keyboard_v2 is

    signal filter : std_logic_vector(7 downto 0) := "00000000";
    signal kbd_clk_filtered : std_logic := '0';
    signal ready_set : std_logic;
    signal parity_pred : std_logic := '1';
    signal incount : unsigned(3 downto 0) := "0000";
    signal shiftin : std_logic_vector(8 downto 0) := "000000000";
    signal state : integer range 0 to 11 := 0;
begin
   
    clk_filter : process
    begin
        wait until clk'event and clk = '1';
        filter(6 downto 0) <= filter(7 downto 1);
        filter(7) <= kbd_clk;
        if filter = x"FF" then 
            kbd_clk_filtered <= '1';
        elsif filter = x"00" then
            kbd_clk_filtered <= '0';
        end if;
    end process;

    process(state)
    begin
        case( state ) is
            when 0 =>
                parity_pred <= '1';
            when 1 =>
                scan_error <= '0';
                ready_set <= '0';
            when 2 | 3 | 4 | 5 | 6 | 7 | 8 | 9 =>
                if kbd_data = '1' then
                    parity_pred <= not parity_pred;
                end if;
                shiftin(7 downto 0) <= shiftin(8 downto 1);
                shiftin(8) <= kbd_data;
            when 10 =>
                shiftin(7 downto 0) <= shiftin(8 downto 1);
                shiftin(8) <= kbd_data;
            when 11 =>
            if shiftin(8) = parity_pred then
                scan_error <= '0';
                else
                scan_error <= '1';
                end if;
                
                scan_parity <= parity_pred;
                scan_code <= shiftin(7 downto 0);
                parity_pred <= '1';
                ready_set <= '1';
        end case ;
    end process;

    process(kbd_clk_filtered)
    begin
        if kbd_clk_filtered'event and kbd_clk_filtered = '0' then
            if reset = '1' then
                state <= 0;
            else
                if state = 11 then
                    state <= 1;
                else 
                    state <= state + 1;
                end if;
            end if;
        end if;
    end process;

    process (enable, ready_set)
    begin
        if enable = '1' then
            scan_ready <= '0';
        elsif ready_set'event then
            scan_ready <= ready_set;
        end if;
    end process;
end arch;

interfaces/keyboard_v2_tb.vhdl
library ieee;
use ieee.std_logic_1164.all;
use ieee.numeric_std.all;
use ieee.std_logic_textio.all;

library std;
use std.textio.all;


entity keyboard_v2_tb is
    constant period : time := 40 ns ; -- Señal de reloj de 25MHz
    constant bit_period : time := 60 us ; -- Keyboard clock ~ 16.7 Khz max
end entity;

architecture arch of keyboard_v2_tb is
    component keyboard_v2 is 
        port(
            kbd_clk, kbd_data, clk : in std_logic;
            reset, enable : in std_logic;
            scan_code : out std_logic_vector(7 downto 0);
            scan_parity : out std_logic;
            scan_ready : out std_logic;
            scan_error : out std_logic
        );
    end component;

    signal clk : std_logic := '0';
    signal reset : std_logic;
    signal kbd_clk : std_logic := '1';
    signal kbd_data : std_logic := 'H';
    signal enable : std_logic := '0';
    signal scan_ready : std_logic := '0';
    signal scan_error : std_logic;
    signal scan_code : std_logic_vector(7 downto 0);
    signal scan_parity : std_logic;

    type dataRecord is record
        code : std_logic_vector(7 downto 0);
        parity : std_logic;
    end record;
 
    type dataArray is array (natural range <>) of dataRecord;
    constant data : dataArray := (
                                    (code => x"3B", parity => '0'),
                                    (code => x"44", parity => '1'),
                                    (code => x"21", parity => '0'), 
                                    (code => x"24", parity => '1')
                                );

    begin 

    UUT : keyboard_v2 port map (kbd_clk, kbd_data, clk, reset, enable, scan_code, scan_parity, scan_ready, scan_error );

    -- Señal de reloj del sistema
    clk <= not clk after (period / 2);
    reset <= '1', '0' after period;

    process
        procedure send_code( sc : dataRecord ) is
        begin
            kbd_clk <= 'H';
            kbd_data <= 'H';
            
            wait for (bit_period/2);
            kbd_data <= '0'; -- Start bit
            
            wait for (bit_period/2);
            kbd_clk <= '0';
            wait for (bit_period/2);
            kbd_clk <= '1';

            for i in 0 to 7 loop
                kbd_data <= sc.code(i);
                
                wait for (bit_period/2);
                kbd_clk <= '0';
                wait for (bit_period/2);
                kbd_clk <= '1';

            end loop;

            -- bit de paridad
            kbd_data <= sc.parity;
            
            wait for (bit_period/2);
            kbd_clk <= '0';
            wait for (bit_period/2);
            kbd_clk <= '1';
            
            -- stop bit
            kbd_data <= '1';
            
            wait for (bit_period/2);
            kbd_clk <= '0';
            wait for (bit_period/2);
            kbd_clk <= '1';
            
            kbd_data <= 'H';
            
            wait for (bit_period * 3);
        end procedure send_code;
    
       begin
        wait for bit_period;
        for i in data'range loop
            send_code(data(i));
        end loop;
        wait;
    end process;

    process
        variable l : line;
    begin
        wait until scan_ready'event and scan_ready = '1';
        
        if scan_error = '1' then
            write (l, string'("Unsuccessful Scan : "));
        else
            write (l, string'("Successful Scan   : "));
        end if;
        
        write (l, string'("Code->"));
        write (l, scan_code);
        write (l, string'(", Parity->"));
        write (l, scan_parity);

        writeline(output, l);
        
    end process;

end arch;

interfaces/keyboard_v2_tb.vcd
$date
  Thu Jun 11 20:11:44 2020
$end
$version
  GHDL v0
$end
$timescale
  1 fs
$end
$scope module standard $end
$upscope $end
$scope module std_logic_1164 $end
$upscope $end
$scope module numeric_std $end
$upscope $end
$scope module textio $end
$upscope $end
$scope module std_logic_textio $end
$upscope $end
$scope module keyboard_v2_tb $end
$var reg 1 ! clk $end
$var reg 1 " reset $end
$var reg 1 # kbd_clk $end
$var reg 1 $ kbd_data $end
$var reg 1 % enable $end
$var reg 1 & scan_ready $end
$var reg 1 ' scan_error $end
$var reg 8 ( scan_code[7:0] $end
$var reg 1 ) scan_parity $end
$scope module uut $end
$var reg 1 * kbd_clk $end
$var reg 1 + kbd_data $end
$var reg 1 , clk $end
$var reg 1 - reset $end
$var reg 1 . enable $end
$var reg 8 / scan_code[7:0] $end
$var reg 1 0 scan_parity $end
$var reg 1 1 scan_ready $end
$var reg 1 2 scan_error $end
$var reg 8 3 filter[7:0] $end
$var reg 1 4 kbd_clk_filtered $end
$var reg 1 5 ready_set $end
$var reg 1 6 parity_pred $end
$var reg 4 7 incount[3:0] $end
$var reg 9 8 shiftin[8:0] $end
$var integer 32 9 state $end
$upscope $end
$upscope $end
$enddefinitions $end
#0
0!
1"
1#
H$
0%
U&
U'
bUUUUUUUU (
U)
1*
H+
0,
1-
0.
bUUUUUUUU /
U0
U1
U2
b00000000 3
04
U5
16
b0000 7
b000000000 8
b0 9
#20000000
1!
1,
b10000000 3
#40000000
0!
0"
0,
0-
#60000000
1!
1,
b11000000 3
#80000000
0!
0,
#100000000
1!
1,
b11100000 3
#120000000
0!
0,
#140000000
1!
1,
b11110000 3
#160000000
0!
0,
#180000000
1!
1,
b11111000 3
#200000000
0!
0,
#220000000
1!
1,
b11111100 3
#240000000
0!
0,
#260000000
1!
1,
b11111110 3
#280000000
0!
0,
#300000000
1!
1,
b11111111 3
